[
  {
    "target_name": "松下電器産業（戦後復興）",
    "scale": "company",
    "period": "1950-1955",
    "story_summary": "GHQ占領下で財閥解体の危機を乗り越え、民生品生産へ転換。熱意ある技術者集団と松下幸之助のリーダーシップで家電王国の礎を築いた。",
    "before_state": "どん底・危機",
    "trigger_type": "外部ショック",
    "action_type": "攻める・挑戦",
    "after_state": "V字回復・大成功",
    "before_hex": "坎",
    "trigger_hex": "震",
    "action_hex": "乾",
    "after_hex": "離",
    "pattern_type": "Shock_Recovery",
    "outcome": "Success",
    "free_tags": [
      "#戦後復興",
      "#家電",
      "#松下幸之助"
    ],
    "source_type": "book",
    "credibility_rank": "A",
    "main_domain": "電機",
    "country": "JP"
  },
  {
    "target_name": "ソニー創業期",
    "scale": "company",
    "period": "1946-1955",
    "story_summary": "井深大と盛田昭夫が焼け野原の東京で東京通信工業を設立。テープレコーダー、トランジスタラジオで世界を席巻する基盤を作った。",
    "before_state": "どん底・危機",
    "trigger_type": "意図的決断",
    "action_type": "攻める・挑戦",
    "after_state": "持続成長・大成功",
    "before_hex": "坎",
    "trigger_hex": "乾",
    "action_hex": "震",
    "after_hex": "離",
    "pattern_type": "Breakthrough",
    "outcome": "Success",
    "free_tags": [
      "#戦後復興",
      "#電機",
      "#イノベーション"
    ],
    "source_type": "book",
    "credibility_rank": "A",
    "main_domain": "電機",
    "country": "JP"
  },
  {
    "target_name": "トヨタ自動車（経営危機からの復活）",
    "scale": "company",
    "period": "1950-1955",
    "story_summary": "朝鮮戦争特需を契機に経営危機を脱出。豊田喜一郎退任後、石田退三体制で生産方式を改革し、品質経営の土台を築いた。",
    "before_state": "どん底・危機",
    "trigger_type": "外部ショック",
    "action_type": "刷新・破壊",
    "after_state": "V字回復・大成功",
    "before_hex": "坎",
    "trigger_hex": "震",
    "action_hex": "離",
    "after_hex": "乾",
    "pattern_type": "Shock_Recovery",
    "outcome": "Success",
    "free_tags": [
      "#自動車",
      "#朝鮮特需",
      "#トヨタ生産方式"
    ],
    "source_type": "book",
    "credibility_rank": "A",
    "main_domain": "自動車",
    "country": "JP"
  },
  {
    "target_name": "本田技研工業（二輪から四輪へ）",
    "scale": "company",
    "period": "1958-1965",
    "story_summary": "本田宗一郎の決断でバイクメーカーから四輪車産業へ参入。通産省の反対を押し切り、軽自動車T360で自動車市場に挑戦。",
    "before_state": "成長痛",
    "trigger_type": "意図的決断",
    "action_type": "攻める・挑戦",
    "after_state": "持続成長・大成功",
    "before_hex": "震",
    "trigger_hex": "乾",
    "action_hex": "乾",
    "after_hex": "離",
    "pattern_type": "Breakthrough",
    "outcome": "Success",
    "free_tags": [
      "#自動車",
      "#本田宗一郎",
      "#規制突破"
    ],
    "source_type": "book",
    "credibility_rank": "A",
    "main_domain": "自動車",
    "country": "JP"
  },
  {
    "target_name": "日本国有鉄道（新幹線開業）",
    "scale": "other",
    "period": "1959-1964",
    "story_summary": "東海道新幹線プロジェクトで世界初の高速鉄道を実現。十河信二総裁の強いリーダーシップで東京オリンピックに間に合わせた。",
    "before_state": "停滞・閉塞",
    "trigger_type": "意図的決断",
    "action_type": "攻める・挑戦",
    "after_state": "V字回復・大成功",
    "before_hex": "艮",
    "trigger_hex": "乾",
    "action_hex": "震",
    "after_hex": "離",
    "pattern_type": "Breakthrough",
    "outcome": "Success",
    "free_tags": [
      "#鉄道",
      "#新幹線",
      "#東京オリンピック"
    ],
    "source_type": "book",
    "credibility_rank": "A",
    "main_domain": "運輸",
    "country": "JP"
  },
  {
    "target_name": "八幡製鉄・富士製鉄合併",
    "scale": "company",
    "period": "1968-1970",
    "story_summary": "日本鉄鋼業界再編の象徴。両社合併で新日本製鐵が誕生し、世界最大の鉄鋼メーカーとなった。国際競争力強化が目的。",
    "before_state": "成長痛",
    "trigger_type": "意図的決断",
    "action_type": "対話・融合",
    "after_state": "持続成長・大成功",
    "before_hex": "震",
    "trigger_hex": "乾",
    "action_hex": "兌",
    "after_hex": "乾",
    "pattern_type": "Steady_Growth",
    "outcome": "Success",
    "free_tags": [
      "#鉄鋼",
      "#合併",
      "#新日鉄"
    ],
    "source_type": "book",
    "credibility_rank": "A",
    "main_domain": "鉄鋼",
    "country": "JP"
  },
  {
    "target_name": "石油ショックと省エネ革命",
    "scale": "country",
    "period": "1973-1979",
    "story_summary": "第一次石油危機で日本経済は大打撃。しかし産業界は省エネ技術開発に邁進し、世界最高水準のエネルギー効率を達成。",
    "before_state": "絶頂・慢心",
    "trigger_type": "外部ショック",
    "action_type": "刷新・破壊",
    "after_state": "変質・新生",
    "before_hex": "乾",
    "trigger_hex": "坎",
    "action_hex": "離",
    "after_hex": "巽",
    "pattern_type": "Shock_Recovery",
    "outcome": "Success",
    "free_tags": [
      "#石油ショック",
      "#省エネ",
      "#産業転換"
    ],
    "source_type": "book",
    "credibility_rank": "A",
    "main_domain": "エネルギー",
    "country": "JP"
  },
  {
    "target_name": "カシオ計算機（電卓戦争）",
    "scale": "company",
    "period": "1965-1975",
    "story_summary": "電卓市場の価格競争で生き残りをかけた戦い。LSI開発と小型化技術で激戦を制し、世界的電卓メーカーに成長。",
    "before_state": "成長痛",
    "trigger_type": "外部ショック",
    "action_type": "攻める・挑戦",
    "after_state": "持続成長・大成功",
    "before_hex": "震",
    "trigger_hex": "坎",
    "action_hex": "乾",
    "after_hex": "離",
    "pattern_type": "Breakthrough",
    "outcome": "Success",
    "free_tags": [
      "#電卓",
      "#LSI",
      "#価格競争"
    ],
    "source_type": "book",
    "credibility_rank": "A",
    "main_domain": "電機",
    "country": "JP"
  },
  {
    "target_name": "セブン-イレブン日本進出",
    "scale": "company",
    "period": "1973-1979",
    "story_summary": "イトーヨーカドーがアメリカのサウスランド社と提携し、日本初のコンビニエンスストアチェーンを展開。小売業革命の始まり。",
    "before_state": "安定・平和",
    "trigger_type": "意図的決断",
    "action_type": "攻める・挑戦",
    "after_state": "持続成長・大成功",
    "before_hex": "坤",
    "trigger_hex": "乾",
    "action_hex": "震",
    "after_hex": "離",
    "pattern_type": "Breakthrough",
    "outcome": "Success",
    "free_tags": [
      "#小売",
      "#コンビニ",
      "#業態革新"
    ],
    "source_type": "book",
    "credibility_rank": "A",
    "main_domain": "小売",
    "country": "JP"
  },
  {
    "target_name": "日産自動車（脱亜入欧戦略）",
    "scale": "company",
    "period": "1958-1970",
    "story_summary": "ブルーバードを軸に乗用車市場を開拓。アメリカ輸出を本格化し、グローバル自動車メーカーへの道を歩み始めた。",
    "before_state": "成長痛",
    "trigger_type": "意図的決断",
    "action_type": "攻める・挑戦",
    "after_state": "持続成長・大成功",
    "before_hex": "震",
    "trigger_hex": "乾",
    "action_hex": "乾",
    "after_hex": "離",
    "pattern_type": "Steady_Growth",
    "outcome": "Success",
    "free_tags": [
      "#自動車",
      "#輸出",
      "#ブルーバード"
    ],
    "source_type": "book",
    "credibility_rank": "A",
    "main_domain": "自動車",
    "country": "JP"
  },
  {
    "target_name": "三井物産（総合商社モデル確立）",
    "scale": "company",
    "period": "1950-1965",
    "story_summary": "財閥解体後に分割された三井物産が再統合。資源・エネルギー・機械など多角的な商社モデルを確立し、日本の貿易を牽引。",
    "before_state": "どん底・危機",
    "trigger_type": "外部ショック",
    "action_type": "対話・融合",
    "after_state": "持続成長・大成功",
    "before_hex": "坎",
    "trigger_hex": "震",
    "action_hex": "兌",
    "after_hex": "乾",
    "pattern_type": "Shock_Recovery",
    "outcome": "Success",
    "free_tags": [
      "#商社",
      "#財閥",
      "#貿易"
    ],
    "source_type": "book",
    "credibility_rank": "A",
    "main_domain": "商社",
    "country": "JP"
  },
  {
    "target_name": "味の素（グルタミン酸ビジネス拡大）",
    "scale": "company",
    "period": "1955-1970",
    "story_summary": "戦後の食糧難を背景に、うま味調味料の需要が急増。東南アジアへの進出も成功し、世界的な食品メーカーへと成長。",
    "before_state": "安定・平和",
    "trigger_type": "意図的決断",
    "action_type": "攻める・挑戦",
    "after_state": "持続成長・大成功",
    "before_hex": "坤",
    "trigger_hex": "乾",
    "action_hex": "乾",
    "after_hex": "離",
    "pattern_type": "Steady_Growth",
    "outcome": "Success",
    "free_tags": [
      "#食品",
      "#海外展開",
      "#うま味"
    ],
    "source_type": "book",
    "credibility_rank": "A",
    "main_domain": "食品",
    "country": "JP"
  },
  {
    "target_name": "東レ（合成繊維への転換）",
    "scale": "company",
    "period": "1951-1965",
    "story_summary": "戦後、レーヨンからナイロン・ポリエステルなど合成繊維へ大転換。デュポンとの技術提携で世界水準の繊維メーカーに。",
    "before_state": "停滞・閉塞",
    "trigger_type": "意図的決断",
    "action_type": "刷新・破壊",
    "after_state": "持続成長・大成功",
    "before_hex": "艮",
    "trigger_hex": "乾",
    "action_hex": "離",
    "after_hex": "乾",
    "pattern_type": "Breakthrough",
    "outcome": "Success",
    "free_tags": [
      "#繊維",
      "#技術提携",
      "#合成繊維"
    ],
    "source_type": "book",
    "credibility_rank": "A",
    "main_domain": "繊維",
    "country": "JP"
  },
  {
    "target_name": "キヤノン（カメラから事務機器へ）",
    "scale": "company",
    "period": "1960-1975",
    "story_summary": "カメラ専業から電卓・複写機市場へ多角化。ゼロックスに挑戦し、事務機器メーカーとしての地位を確立。",
    "before_state": "安定・平和",
    "trigger_type": "意図的決断",
    "action_type": "攻める・挑戦",
    "after_state": "持続成長・大成功",
    "before_hex": "坤",
    "trigger_hex": "乾",
    "action_hex": "震",
    "after_hex": "離",
    "pattern_type": "Breakthrough",
    "outcome": "Success",
    "free_tags": [
      "#カメラ",
      "#事務機器",
      "#多角化"
    ],
    "source_type": "book",
    "credibility_rank": "A",
    "main_domain": "電機",
    "country": "JP"
  },
  {
    "target_name": "ダイエー創業期",
    "scale": "company",
    "period": "1957-1972",
    "story_summary": "中内功が価格破壊を武器にスーパーマーケットチェーンを急拡大。流通革命を起こし、小売業界の構造を変革した。",
    "before_state": "どん底・危機",
    "trigger_type": "意図的決断",
    "action_type": "攻める・挑戦",
    "after_state": "持続成長・大成功",
    "before_hex": "坎",
    "trigger_hex": "乾",
    "action_hex": "震",
    "after_hex": "離",
    "pattern_type": "Breakthrough",
    "outcome": "Success",
    "free_tags": [
      "#小売",
      "#流通革命",
      "#中内功"
    ],
    "source_type": "book",
    "credibility_rank": "A",
    "main_domain": "小売",
    "country": "JP"
  },
  {
    "target_name": "日本電気（コンピュータ事業参入）",
    "scale": "company",
    "period": "1958-1970",
    "story_summary": "通信機器メーカーからコンピュータ事業へ本格参入。国産コンピュータ開発でIBMに対抗し、情報産業の礎を築いた。",
    "before_state": "安定・平和",
    "trigger_type": "意図的決断",
    "action_type": "攻める・挑戦",
    "after_state": "持続成長・大成功",
    "before_hex": "坤",
    "trigger_hex": "乾",
    "action_hex": "震",
    "after_hex": "離",
    "pattern_type": "Breakthrough",
    "outcome": "Success",
    "free_tags": [
      "#コンピュータ",
      "#情報産業",
      "#NEC"
    ],
    "source_type": "book",
    "credibility_rank": "A",
    "main_domain": "電機",
    "country": "JP"
  },
  {
    "target_name": "川崎重工業（重工業復興）",
    "scale": "company",
    "period": "1950-1965",
    "story_summary": "戦後の財閥解体から復興し、造船・航空機・鉄道車両の総合重工業メーカーとして再生。新幹線車両製造にも参画。",
    "before_state": "どん底・危機",
    "trigger_type": "外部ショック",
    "action_type": "攻める・挑戦",
    "after_state": "持続成長・大成功",
    "before_hex": "坎",
    "trigger_hex": "震",
    "action_hex": "乾",
    "after_hex": "離",
    "pattern_type": "Shock_Recovery",
    "outcome": "Success",
    "free_tags": [
      "#重工業",
      "#造船",
      "#新幹線"
    ],
    "source_type": "book",
    "credibility_rank": "A",
    "main_domain": "重工業",
    "country": "JP"
  },
  {
    "target_name": "武田薬品工業（ビタミン事業成功）",
    "scale": "company",
    "period": "1950-1965",
    "story_summary": "戦後の栄養不足を背景にビタミン剤アリナミンが大ヒット。製薬業界トップの座を確立し、研究開発型企業に転換。",
    "before_state": "安定・平和",
    "trigger_type": "偶発・出会い",
    "action_type": "攻める・挑戦",
    "after_state": "持続成長・大成功",
    "before_hex": "坤",
    "trigger_hex": "巽",
    "action_hex": "乾",
    "after_hex": "離",
    "pattern_type": "Breakthrough",
    "outcome": "Success",
    "free_tags": [
      "#製薬",
      "#アリナミン",
      "#ビタミン"
    ],
    "source_type": "book",
    "credibility_rank": "A",
    "main_domain": "製薬",
    "country": "JP"
  },
  {
    "target_name": "ヤマハ（楽器から多角化）",
    "scale": "company",
    "period": "1955-1975",
    "story_summary": "楽器製造から二輪車、スポーツ用品へと多角化。音楽教室事業も展開し、総合レジャー企業へと成長。",
    "before_state": "安定・平和",
    "trigger_type": "意図的決断",
    "action_type": "分散・スピンオフ",
    "after_state": "持続成長・大成功",
    "before_hex": "坤",
    "trigger_hex": "乾",
    "action_hex": "巽",
    "after_hex": "離",
    "pattern_type": "Steady_Growth",
    "outcome": "Success",
    "free_tags": [
      "#楽器",
      "#多角化",
      "#二輪車"
    ],
    "source_type": "book",
    "credibility_rank": "A",
    "main_domain": "製造業",
    "country": "JP"
  },
  {
    "target_name": "サントリー（ビール市場参入）",
    "scale": "company",
    "period": "1963-1979",
    "story_summary": "ウイスキーメーカーがビール市場に本格参入。キリン・アサヒの牙城に挑むも苦戦。長期戦を覚悟した耐久戦略を展開。",
    "before_state": "絶頂・慢心",
    "trigger_type": "意図的決断",
    "action_type": "攻める・挑戦",
    "after_state": "現状維持・延命",
    "before_hex": "乾",
    "trigger_hex": "乾",
    "action_hex": "震",
    "after_hex": "艮",
    "pattern_type": "Endurance",
    "outcome": "Mixed",
    "free_tags": [
      "#ビール",
      "#新規参入",
      "#苦戦"
    ],
    "source_type": "book",
    "credibility_rank": "A",
    "main_domain": "飲料",
    "country": "JP"
  },
  {
    "target_name": "シャープ（電卓LSI開発）",
    "scale": "company",
    "period": "1964-1975",
    "story_summary": "世界初のオールトランジスタ電卓を開発。LSI技術を独自開発し、電卓戦争を勝ち抜いて電子機器メーカーに転身。",
    "before_state": "安定・平和",
    "trigger_type": "意図的決断",
    "action_type": "攻める・挑戦",
    "after_state": "持続成長・大成功",
    "before_hex": "坤",
    "trigger_hex": "乾",
    "action_hex": "震",
    "after_hex": "離",
    "pattern_type": "Breakthrough",
    "outcome": "Success",
    "free_tags": [
      "#電卓",
      "#LSI",
      "#シャープ"
    ],
    "source_type": "book",
    "credibility_rank": "A",
    "main_domain": "電機",
    "country": "JP"
  },
  {
    "target_name": "炭鉱産業の衰退",
    "scale": "other",
    "period": "1960-1975",
    "story_summary": "石油へのエネルギー転換により国内炭鉱が次々と閉山。三井三池争議に象徴される労使対立を経て、産業構造が激変。",
    "before_state": "絶頂・慢心",
    "trigger_type": "外部ショック",
    "action_type": "捨てる・撤退",
    "after_state": "崩壊・消滅",
    "before_hex": "乾",
    "trigger_hex": "坎",
    "action_hex": "艮",
    "after_hex": "坤",
    "pattern_type": "Slow_Decline",
    "outcome": "Failure",
    "free_tags": [
      "#炭鉱",
      "#エネルギー転換",
      "#産業衰退"
    ],
    "source_type": "book",
    "credibility_rank": "A",
    "main_domain": "エネルギー",
    "country": "JP"
  },
  {
    "target_name": "田中角栄（列島改造論）",
    "scale": "individual",
    "period": "1972-1974",
    "story_summary": "日本列島改造論を掲げて首相に就任。高速道路・新幹線網の整備を推進したが、石油ショックとインフレで政策が頓挫。",
    "before_state": "絶頂・慢心",
    "trigger_type": "外部ショック",
    "action_type": "攻める・挑戦",
    "after_state": "迷走・混乱",
    "before_hex": "乾",
    "trigger_hex": "坎",
    "action_hex": "震",
    "after_hex": "坎",
    "pattern_type": "Hubris_Collapse",
    "outcome": "Failure",
    "free_tags": [
      "#政治",
      "#列島改造",
      "#石油ショック"
    ],
    "source_type": "book",
    "credibility_rank": "A",
    "main_domain": "政治",
    "country": "JP"
  },
  {
    "target_name": "吉田茂（サンフランシスコ講和）",
    "scale": "individual",
    "period": "1950-1952",
    "story_summary": "サンフランシスコ平和条約締結で日本の独立を回復。親米路線で西側陣営に組み込まれ、経済復興の基盤を確立。",
    "before_state": "どん底・危機",
    "trigger_type": "意図的決断",
    "action_type": "対話・融合",
    "after_state": "V字回復・大成功",
    "before_hex": "坎",
    "trigger_hex": "乾",
    "action_hex": "兌",
    "after_hex": "離",
    "pattern_type": "Shock_Recovery",
    "outcome": "Success",
    "free_tags": [
      "#政治",
      "#講和条約",
      "#独立回復"
    ],
    "source_type": "book",
    "credibility_rank": "A",
    "main_domain": "政治",
    "country": "JP"
  },
  {
    "target_name": "池田勇人（所得倍増計画）",
    "scale": "individual",
    "period": "1960-1964",
    "story_summary": "所得倍増計画を掲げ高度経済成長を主導。安保闘争後の社会不安を経済成長で克服し、日本を経済大国へ導いた。",
    "before_state": "混乱・カオス",
    "trigger_type": "意図的決断",
    "action_type": "攻める・挑戦",
    "after_state": "持続成長・大成功",
    "before_hex": "坎",
    "trigger_hex": "乾",
    "action_hex": "乾",
    "after_hex": "離",
    "pattern_type": "Breakthrough",
    "outcome": "Success",
    "free_tags": [
      "#政治",
      "#所得倍増",
      "#高度成長"
    ],
    "source_type": "book",
    "credibility_rank": "A",
    "main_domain": "政治",
    "country": "JP"
  },
  {
    "target_name": "美空ひばり（戦後歌謡の女王）",
    "scale": "individual",
    "period": "1949-1965",
    "story_summary": "12歳でデビューし戦後日本を代表する歌手に成長。暴力団関係のスキャンダルも乗り越え、国民的歌手の地位を確立。",
    "before_state": "どん底・危機",
    "trigger_type": "偶発・出会い",
    "action_type": "攻める・挑戦",
    "after_state": "持続成長・大成功",
    "before_hex": "坎",
    "trigger_hex": "巽",
    "action_hex": "乾",
    "after_hex": "離",
    "pattern_type": "Breakthrough",
    "outcome": "Success",
    "free_tags": [
      "#歌手",
      "#戦後文化",
      "#国民的スター"
    ],
    "source_type": "book",
    "credibility_rank": "A",
    "main_domain": "芸能",
    "country": "JP"
  },
  {
    "target_name": "黒澤明（世界的映画監督へ）",
    "scale": "individual",
    "period": "1950-1965",
    "story_summary": "羅生門でベネチア映画祭グランプリを受賞。七人の侍など傑作を連発し、日本映画を世界に知らしめた巨匠に。",
    "before_state": "安定・平和",
    "trigger_type": "偶発・出会い",
    "action_type": "攻める・挑戦",
    "after_state": "持続成長・大成功",
    "before_hex": "坤",
    "trigger_hex": "巽",
    "action_hex": "乾",
    "after_hex": "離",
    "pattern_type": "Breakthrough",
    "outcome": "Success",
    "free_tags": [
      "#映画",
      "#世界進出",
      "#羅生門"
    ],
    "source_type": "book",
    "credibility_rank": "A",
    "main_domain": "芸能",
    "country": "JP"
  },
  {
    "target_name": "手塚治虫（漫画の神様誕生）",
    "scale": "individual",
    "period": "1947-1963",
    "story_summary": "新宝島で漫画表現を革新。鉄腕アトムでTVアニメの先駆けとなり、日本漫画・アニメ産業の基礎を一人で築いた。",
    "before_state": "どん底・危機",
    "trigger_type": "意図的決断",
    "action_type": "攻める・挑戦",
    "after_state": "持続成長・大成功",
    "before_hex": "坎",
    "trigger_hex": "乾",
    "action_hex": "震",
    "after_hex": "離",
    "pattern_type": "Breakthrough",
    "outcome": "Success",
    "free_tags": [
      "#漫画",
      "#アニメ",
      "#手塚治虫"
    ],
    "source_type": "book",
    "credibility_rank": "A",
    "main_domain": "芸能",
    "country": "JP"
  },
  {
    "target_name": "王貞治（ホームラン王への道）",
    "scale": "individual",
    "period": "1959-1977",
    "story_summary": "一本足打法を確立し、通算868本塁打の世界記録を達成。日本プロ野球を代表するスーパースターとして君臨。",
    "before_state": "成長痛",
    "trigger_type": "偶発・出会い",
    "action_type": "耐える・潜伏",
    "after_state": "持続成長・大成功",
    "before_hex": "震",
    "trigger_hex": "巽",
    "action_hex": "坤",
    "after_hex": "離",
    "pattern_type": "Endurance",
    "outcome": "Success",
    "free_tags": [
      "#野球",
      "#ホームラン王",
      "#王貞治"
    ],
    "source_type": "book",
    "credibility_rank": "A",
    "main_domain": "スポーツ",
    "country": "JP"
  },
  {
    "target_name": "三菱グループ（財閥解体からの再結集）",
    "scale": "company",
    "period": "1950-1970",
    "story_summary": "GHQによる財閥解体後、金曜会を中心にグループ企業が緩やかに再結集。重工業・銀行・商事の三本柱で企業集団を形成。",
    "before_state": "どん底・危機",
    "trigger_type": "外部ショック",
    "action_type": "対話・融合",
    "after_state": "持続成長・大成功",
    "before_hex": "坎",
    "trigger_hex": "震",
    "action_hex": "兌",
    "after_hex": "乾",
    "pattern_type": "Shock_Recovery",
    "outcome": "Success",
    "free_tags": [
      "#財閥",
      "#企業集団",
      "#三菱"
    ],
    "source_type": "book",
    "credibility_rank": "A",
    "main_domain": "複合企業",
    "country": "JP"
  },
  {
    "target_name": "三井財閥（近代化と多角化）",
    "scale": "company",
    "period": "1900-1920",
    "story_summary": "江戸時代からの両替商から近代財閥へ転換。三井銀行・三井物産・三井鉱山を核に金融・商事・鉱業の三本柱を確立。",
    "before_state": "安定・平和",
    "trigger_type": "外部ショック",
    "action_type": "刷新・破壊",
    "after_state": "持続成長・大成功",
    "before_hex": "坤",
    "trigger_hex": "震",
    "action_hex": "離",
    "after_hex": "乾",
    "pattern_type": "Breakthrough",
    "outcome": "Success",
    "free_tags": [
      "#財閥",
      "#三井",
      "#近代化"
    ],
    "source_type": "book",
    "credibility_rank": "A",
    "main_domain": "複合企業",
    "country": "JP"
  },
  {
    "target_name": "住友財閥（別子銅山から金融へ）",
    "scale": "company",
    "period": "1900-1930",
    "story_summary": "別子銅山を基盤に住友銀行・住友金属を設立。堅実経営で三大財閥の一角に成長。鉱害問題にも先進的に対応。",
    "before_state": "安定・平和",
    "trigger_type": "意図的決断",
    "action_type": "攻める・挑戦",
    "after_state": "持続成長・大成功",
    "before_hex": "坤",
    "trigger_hex": "乾",
    "action_hex": "乾",
    "after_hex": "乾",
    "pattern_type": "Steady_Growth",
    "outcome": "Success",
    "free_tags": [
      "#財閥",
      "#住友",
      "#別子銅山"
    ],
    "source_type": "book",
    "credibility_rank": "A",
    "main_domain": "複合企業",
    "country": "JP"
  },
  {
    "target_name": "鈴木商店（急成長と破綻）",
    "scale": "company",
    "period": "1900-1927",
    "story_summary": "金子直吉の指揮下で総合商社に急成長。第一次大戦で巨利を得たが、戦後恐慌と台湾銀行問題で破綻し消滅。",
    "before_state": "絶頂・慢心",
    "trigger_type": "外部ショック",
    "action_type": "逃げる・放置",
    "after_state": "崩壊・消滅",
    "before_hex": "乾",
    "trigger_hex": "坎",
    "action_hex": "坤",
    "after_hex": "坎",
    "pattern_type": "Hubris_Collapse",
    "outcome": "Failure",
    "free_tags": [
      "#商社",
      "#鈴木商店",
      "#金融恐慌"
    ],
    "source_type": "book",
    "credibility_rank": "A",
    "main_domain": "商社",
    "country": "JP"
  },
  {
    "target_name": "日本製鉄（戦時体制下の拡大）",
    "scale": "company",
    "period": "1934-1945",
    "story_summary": "官営八幡製鉄所を核に民間製鉄会社を統合。国策会社として軍需生産を担い、戦時下で急拡大したが敗戦で解体。",
    "before_state": "成長痛",
    "trigger_type": "外部ショック",
    "action_type": "対話・融合",
    "after_state": "崩壊・消滅",
    "before_hex": "震",
    "trigger_hex": "震",
    "action_hex": "兌",
    "after_hex": "坎",
    "pattern_type": "Failed_Attempt",
    "outcome": "Failure",
    "free_tags": [
      "#鉄鋼",
      "#国策会社",
      "#戦時体制"
    ],
    "source_type": "book",
    "credibility_rank": "A",
    "main_domain": "鉄鋼",
    "country": "JP"
  },
  {
    "target_name": "南満州鉄道（満鉄経営）",
    "scale": "company",
    "period": "1906-1945",
    "story_summary": "日露戦争後に設立された国策会社。鉄道経営から満州開発・調査まで担う巨大組織に成長したが、敗戦で全てを失った。",
    "before_state": "成長痛",
    "trigger_type": "意図的決断",
    "action_type": "攻める・挑戦",
    "after_state": "崩壊・消滅",
    "before_hex": "震",
    "trigger_hex": "乾",
    "action_hex": "乾",
    "after_hex": "坎",
    "pattern_type": "Failed_Attempt",
    "outcome": "Failure",
    "free_tags": [
      "#満鉄",
      "#国策会社",
      "#植民地経営"
    ],
    "source_type": "book",
    "credibility_rank": "A",
    "main_domain": "運輸",
    "country": "JP"
  },
  {
    "target_name": "中島飛行機（航空機産業の興亡）",
    "scale": "company",
    "period": "1917-1945",
    "story_summary": "中島知久平が創業し、三菱と並ぶ航空機メーカーに成長。零戦エンジン等を製造したが、敗戦で解体されスバルの母体に。",
    "before_state": "成長痛",
    "trigger_type": "外部ショック",
    "action_type": "攻める・挑戦",
    "after_state": "崩壊・消滅",
    "before_hex": "震",
    "trigger_hex": "震",
    "action_hex": "乾",
    "after_hex": "坎",
    "pattern_type": "Failed_Attempt",
    "outcome": "Failure",
    "free_tags": [
      "#航空機",
      "#中島飛行機",
      "#軍需産業"
    ],
    "source_type": "book",
    "credibility_rank": "A",
    "main_domain": "重工業",
    "country": "JP"
  },
  {
    "target_name": "野口遵（日窒コンツェルン）",
    "scale": "individual",
    "period": "1906-1945",
    "story_summary": "水力発電と電気化学工業を結びつけ、朝鮮・満州で化学コンビナートを建設。新興財閥を形成したが敗戦で全てを失う。",
    "before_state": "どん底・危機",
    "trigger_type": "意図的決断",
    "action_type": "攻める・挑戦",
    "after_state": "崩壊・消滅",
    "before_hex": "坎",
    "trigger_hex": "乾",
    "action_hex": "震",
    "after_hex": "坎",
    "pattern_type": "Failed_Attempt",
    "outcome": "Failure",
    "free_tags": [
      "#化学",
      "#新興財閥",
      "#植民地"
    ],
    "source_type": "book",
    "credibility_rank": "A",
    "main_domain": "化学",
    "country": "JP"
  },
  {
    "target_name": "豊田佐吉（自動織機発明）",
    "scale": "individual",
    "period": "1900-1930",
    "story_summary": "貧農の子から発明家へ。自動織機を発明し、豊田自動織機を設立。その特許料がトヨタ自動車創業の資金となった。",
    "before_state": "どん底・危機",
    "trigger_type": "意図的決断",
    "action_type": "攻める・挑戦",
    "after_state": "持続成長・大成功",
    "before_hex": "坎",
    "trigger_hex": "乾",
    "action_hex": "震",
    "after_hex": "離",
    "pattern_type": "Breakthrough",
    "outcome": "Success",
    "free_tags": [
      "#発明家",
      "#豊田佐吉",
      "#自動織機"
    ],
    "source_type": "book",
    "credibility_rank": "A",
    "main_domain": "製造業",
    "country": "JP"
  },
  {
    "target_name": "渋沢栄一（近代資本主義の父）",
    "scale": "individual",
    "period": "1900-1916",
    "story_summary": "大蔵省を辞し民間へ転身。第一国立銀行を皮切りに500以上の企業設立に関与し、日本資本主義の基盤を築いた。",
    "before_state": "安定・平和",
    "trigger_type": "意図的決断",
    "action_type": "攻める・挑戦",
    "after_state": "持続成長・大成功",
    "before_hex": "坤",
    "trigger_hex": "乾",
    "action_hex": "震",
    "after_hex": "乾",
    "pattern_type": "Breakthrough",
    "outcome": "Success",
    "free_tags": [
      "#実業家",
      "#渋沢栄一",
      "#銀行"
    ],
    "source_type": "book",
    "credibility_rank": "A",
    "main_domain": "金融",
    "country": "JP"
  },
  {
    "target_name": "大正デモクラシー",
    "scale": "country",
    "period": "1912-1926",
    "story_summary": "大正期に政党政治・普通選挙運動が活発化。民主主義的気運が高まったが、昭和恐慌と軍部台頭で後退していく。",
    "before_state": "成長痛",
    "trigger_type": "偶発・出会い",
    "action_type": "刷新・破壊",
    "after_state": "現状維持・延命",
    "before_hex": "震",
    "trigger_hex": "巽",
    "action_hex": "離",
    "after_hex": "艮",
    "pattern_type": "Failed_Attempt",
    "outcome": "Mixed",
    "free_tags": [
      "#政治",
      "#デモクラシー",
      "#普通選挙"
    ],
    "source_type": "book",
    "credibility_rank": "A",
    "main_domain": "政治",
    "country": "JP"
  },
  {
    "target_name": "関東大震災からの復興",
    "scale": "country",
    "period": "1923-1930",
    "story_summary": "1923年の大震災で東京・横浜が壊滅。後藤新平の都市計画で近代的な首都に再建されたが、復興費用が財政を圧迫。",
    "before_state": "絶頂・慢心",
    "trigger_type": "外部ショック",
    "action_type": "刷新・破壊",
    "after_state": "変質・新生",
    "before_hex": "乾",
    "trigger_hex": "坎",
    "action_hex": "離",
    "after_hex": "巽",
    "pattern_type": "Shock_Recovery",
    "outcome": "Mixed",
    "free_tags": [
      "#震災",
      "#都市計画",
      "#後藤新平"
    ],
    "source_type": "book",
    "credibility_rank": "A",
    "main_domain": "都市",
    "country": "JP"
  },
  {
    "target_name": "昭和金融恐慌",
    "scale": "country",
    "period": "1927-1929",
    "story_summary": "関東大震災の不良債権処理の遅れから銀行取付騒ぎが発生。中小銀行が相次いで破綻し、財閥系銀行への集中が進んだ。",
    "before_state": "成長痛",
    "trigger_type": "内部崩壊",
    "action_type": "耐える・潜伏",
    "after_state": "混乱・カオス",
    "before_hex": "震",
    "trigger_hex": "坎",
    "action_hex": "坤",
    "after_hex": "坎",
    "pattern_type": "Failed_Attempt",
    "outcome": "Failure",
    "free_tags": [
      "#金融危機",
      "#銀行",
      "#恐慌"
    ],
    "source_type": "book",
    "credibility_rank": "A",
    "main_domain": "金融",
    "country": "JP"
  },
  {
    "target_name": "満州事変と軍部台頭",
    "scale": "country",
    "period": "1931-1937",
    "story_summary": "関東軍の独走で満州事変が勃発。軍部が政治に介入し、政党政治は崩壊。日本は戦争への道を歩み始める。",
    "before_state": "混乱・カオス",
    "trigger_type": "内部崩壊",
    "action_type": "攻める・挑戦",
    "after_state": "混乱・カオス",
    "before_hex": "坎",
    "trigger_hex": "震",
    "action_hex": "乾",
    "after_hex": "坎",
    "pattern_type": "Failed_Attempt",
    "outcome": "Failure",
    "free_tags": [
      "#軍部",
      "#満州事変",
      "#政治崩壊"
    ],
    "source_type": "book",
    "credibility_rank": "A",
    "main_domain": "政治",
    "country": "JP"
  },
  {
    "target_name": "日本郵船（海運王国形成）",
    "scale": "company",
    "period": "1900-1920",
    "story_summary": "三菱と共同運輸の合併で誕生。政府補助金を受けて欧米航路を開設し、世界有数の海運会社に成長。",
    "before_state": "成長痛",
    "trigger_type": "意図的決断",
    "action_type": "対話・融合",
    "after_state": "持続成長・大成功",
    "before_hex": "震",
    "trigger_hex": "乾",
    "action_hex": "兌",
    "after_hex": "乾",
    "pattern_type": "Steady_Growth",
    "outcome": "Success",
    "free_tags": [
      "#海運",
      "#日本郵船",
      "#政府補助"
    ],
    "source_type": "book",
    "credibility_rank": "A",
    "main_domain": "運輸",
    "country": "JP"
  },
  {
    "target_name": "阪急電鉄（沿線開発モデル）",
    "scale": "company",
    "period": "1907-1940",
    "story_summary": "小林一三が鉄道と沿線開発を一体化したビジネスモデルを確立。宝塚歌劇・百貨店・住宅地開発で収益を多角化。",
    "before_state": "どん底・危機",
    "trigger_type": "意図的決断",
    "action_type": "攻める・挑戦",
    "after_state": "持続成長・大成功",
    "before_hex": "坎",
    "trigger_hex": "乾",
    "action_hex": "震",
    "after_hex": "乾",
    "pattern_type": "Breakthrough",
    "outcome": "Success",
    "free_tags": [
      "#鉄道",
      "#小林一三",
      "#沿線開発"
    ],
    "source_type": "book",
    "credibility_rank": "A",
    "main_domain": "運輸",
    "country": "JP"
  },
  {
    "target_name": "明治製糖（製糖業の発展）",
    "scale": "company",
    "period": "1906-1940",
    "story_summary": "台湾統治を背景に製糖業が発展。明治製糖は台湾で大規模プランテーションを展開し、日本の砂糖自給に貢献。",
    "before_state": "成長痛",
    "trigger_type": "意図的決断",
    "action_type": "攻める・挑戦",
    "after_state": "持続成長・大成功",
    "before_hex": "震",
    "trigger_hex": "乾",
    "action_hex": "乾",
    "after_hex": "離",
    "pattern_type": "Steady_Growth",
    "outcome": "Success",
    "free_tags": [
      "#製糖",
      "#台湾",
      "#植民地"
    ],
    "source_type": "book",
    "credibility_rank": "A",
    "main_domain": "食品",
    "country": "JP"
  },
  {
    "target_name": "王子製紙（製紙業の近代化）",
    "scale": "company",
    "period": "1900-1945",
    "story_summary": "渋沢栄一が創設した製紙会社が合併を重ねて巨大企業に。新聞用紙の国産化を実現し、戦時下では軍需物資も製造。",
    "before_state": "成長痛",
    "trigger_type": "意図的決断",
    "action_type": "対話・融合",
    "after_state": "持続成長・大成功",
    "before_hex": "震",
    "trigger_hex": "乾",
    "action_hex": "兌",
    "after_hex": "乾",
    "pattern_type": "Steady_Growth",
    "outcome": "Success",
    "free_tags": [
      "#製紙",
      "#王子製紙",
      "#近代化"
    ],
    "source_type": "book",
    "credibility_rank": "A",
    "main_domain": "製造業",
    "country": "JP"
  },
  {
    "target_name": "薩摩藩の殖産興業",
    "scale": "country",
    "period": "1851-1867",
    "story_summary": "島津斉彬が集成館事業を推進。反射炉・紡績工場など近代工業を導入し、維新後の殖産興業政策の先駆けとなった。",
    "before_state": "停滞・閉塞",
    "trigger_type": "意図的決断",
    "action_type": "刷新・破壊",
    "after_state": "変質・新生",
    "before_hex": "艮",
    "trigger_hex": "乾",
    "action_hex": "離",
    "after_hex": "震",
    "pattern_type": "Breakthrough",
    "outcome": "Success",
    "free_tags": [
      "#藩政改革",
      "#島津斉彬",
      "#集成館"
    ],
    "source_type": "book",
    "credibility_rank": "A",
    "main_domain": "製造業",
    "country": "JP"
  },
  {
    "target_name": "長州藩の倒幕運動",
    "scale": "country",
    "period": "1858-1868",
    "story_summary": "尊王攘夷から開国倒幕へ路線転換。薩長同盟を結び、戊辰戦争で幕府を打倒。明治政府の中核を担う人材を輩出。",
    "before_state": "混乱・カオス",
    "trigger_type": "意図的決断",
    "action_type": "対話・融合",
    "after_state": "V字回復・大成功",
    "before_hex": "坎",
    "trigger_hex": "乾",
    "action_hex": "兌",
    "after_hex": "離",
    "pattern_type": "Crisis_Pivot",
    "outcome": "Success",
    "free_tags": [
      "#幕末",
      "#長州藩",
      "#薩長同盟"
    ],
    "source_type": "book",
    "credibility_rank": "A",
    "main_domain": "政治",
    "country": "JP"
  },
  {
    "target_name": "徳川幕府の崩壊",
    "scale": "country",
    "period": "1853-1868",
    "story_summary": "黒船来航で開国を迫られ、体制動揺。大政奉還で政権を朝廷に返上したが、戊辰戦争で敗北し260年の幕藩体制が終焉。",
    "before_state": "停滞・閉塞",
    "trigger_type": "外部ショック",
    "action_type": "逃げる・放置",
    "after_state": "崩壊・消滅",
    "before_hex": "艮",
    "trigger_hex": "震",
    "action_hex": "坤",
    "after_hex": "坎",
    "pattern_type": "Hubris_Collapse",
    "outcome": "Failure",
    "free_tags": [
      "#幕末",
      "#徳川幕府",
      "#大政奉還"
    ],
    "source_type": "book",
    "credibility_rank": "A",
    "main_domain": "政治",
    "country": "JP"
  },
  {
    "target_name": "明治維新",
    "scale": "country",
    "period": "1868-1877",
    "story_summary": "王政復古から廃藩置県・殖産興業へ。欧米列強に対抗するため急速な近代化を推進し、アジア初の近代国家を建設。",
    "before_state": "混乱・カオス",
    "trigger_type": "意図的決断",
    "action_type": "刷新・破壊",
    "after_state": "変質・新生",
    "before_hex": "坎",
    "trigger_hex": "乾",
    "action_hex": "離",
    "after_hex": "震",
    "pattern_type": "Crisis_Pivot",
    "outcome": "Success",
    "free_tags": [
      "#明治維新",
      "#近代化",
      "#殖産興業"
    ],
    "source_type": "book",
    "credibility_rank": "A",
    "main_domain": "政治",
    "country": "JP"
  },
  {
    "target_name": "日清戦争勝利",
    "scale": "country",
    "period": "1894-1895",
    "story_summary": "朝鮮半島の覇権を巡り清国と開戦。近代化した日本軍が勝利し、台湾を獲得。アジアの新興強国として国際認知を得た。",
    "before_state": "成長痛",
    "trigger_type": "外部ショック",
    "action_type": "攻める・挑戦",
    "after_state": "V字回復・大成功",
    "before_hex": "震",
    "trigger_hex": "震",
    "action_hex": "乾",
    "after_hex": "離",
    "pattern_type": "Breakthrough",
    "outcome": "Success",
    "free_tags": [
      "#日清戦争",
      "#近代化",
      "#台湾"
    ],
    "source_type": "book",
    "credibility_rank": "A",
    "main_domain": "軍事",
    "country": "JP"
  },
  {
    "target_name": "福沢諭吉（啓蒙思想家）",
    "scale": "individual",
    "period": "1860-1890",
    "story_summary": "咸臨丸で渡米後、西洋思想を紹介。学問のすゝめで独立自尊を説き、慶應義塾を創立して近代日本の人材育成に貢献。",
    "before_state": "安定・平和",
    "trigger_type": "偶発・出会い",
    "action_type": "攻める・挑戦",
    "after_state": "持続成長・大成功",
    "before_hex": "坤",
    "trigger_hex": "巽",
    "action_hex": "乾",
    "after_hex": "離",
    "pattern_type": "Breakthrough",
    "outcome": "Success",
    "free_tags": [
      "#教育",
      "#福沢諭吉",
      "#啓蒙"
    ],
    "source_type": "book",
    "credibility_rank": "A",
    "main_domain": "教育",
    "country": "JP"
  },
  {
    "target_name": "大久保利通（近代国家建設）",
    "scale": "individual",
    "period": "1868-1878",
    "story_summary": "維新の三傑の一人として廃藩置県・殖産興業を主導。内務卿として近代国家の基盤を築いたが、不平士族に暗殺された。",
    "before_state": "混乱・カオス",
    "trigger_type": "意図的決断",
    "action_type": "刷新・破壊",
    "after_state": "変質・新生",
    "before_hex": "坎",
    "trigger_hex": "乾",
    "action_hex": "離",
    "after_hex": "震",
    "pattern_type": "Crisis_Pivot",
    "outcome": "Success",
    "free_tags": [
      "#明治維新",
      "#大久保利通",
      "#内務卿"
    ],
    "source_type": "book",
    "credibility_rank": "A",
    "main_domain": "政治",
    "country": "JP"
  },
  {
    "target_name": "伊藤博文（憲法制定）",
    "scale": "individual",
    "period": "1881-1889",
    "story_summary": "欧州視察でプロイセン型憲法を学び、大日本帝国憲法を起草。初代内閣総理大臣として立憲君主制の基礎を確立。",
    "before_state": "成長痛",
    "trigger_type": "意図的決断",
    "action_type": "攻める・挑戦",
    "after_state": "安定成長・成功",
    "before_hex": "震",
    "trigger_hex": "乾",
    "action_hex": "乾",
    "after_hex": "巽",
    "pattern_type": "Breakthrough",
    "outcome": "Success",
    "free_tags": [
      "#憲法",
      "#伊藤博文",
      "#立憲政治"
    ],
    "source_type": "book",
    "credibility_rank": "A",
    "main_domain": "政治",
    "country": "JP"
  },
  {
    "target_name": "坂本龍馬（薩長同盟仲介）",
    "scale": "individual",
    "period": "1864-1867",
    "story_summary": "脱藩浪士から倒幕の立役者へ。犬猿の仲だった薩摩と長州を仲介し、薩長同盟を実現。大政奉還を導いたが暗殺された。",
    "before_state": "混乱・カオス",
    "trigger_type": "偶発・出会い",
    "action_type": "対話・融合",
    "after_state": "V字回復・大成功",
    "before_hex": "坎",
    "trigger_hex": "巽",
    "action_hex": "兌",
    "after_hex": "離",
    "pattern_type": "Crisis_Pivot",
    "outcome": "Success",
    "free_tags": [
      "#幕末",
      "#坂本龍馬",
      "#薩長同盟"
    ],
    "source_type": "book",
    "credibility_rank": "A",
    "main_domain": "政治",
    "country": "JP"
  },
  {
    "target_name": "勝海舟（江戸無血開城）",
    "scale": "individual",
    "period": "1868",
    "story_summary": "幕臣として西郷隆盛と交渉し、江戸城の無血開城を実現。百万都市江戸を戦火から救い、内戦の拡大を防いだ。",
    "before_state": "どん底・危機",
    "trigger_type": "外部ショック",
    "action_type": "対話・融合",
    "after_state": "縮小安定・生存",
    "before_hex": "坎",
    "trigger_hex": "震",
    "action_hex": "兌",
    "after_hex": "艮",
    "pattern_type": "Crisis_Pivot",
    "outcome": "Success",
    "free_tags": [
      "#幕末",
      "#勝海舟",
      "#江戸開城"
    ],
    "source_type": "book",
    "credibility_rank": "A",
    "main_domain": "政治",
    "country": "JP"
  },
  {
    "target_name": "トヨタ自動車創業",
    "scale": "company",
    "period": "1933-1945",
    "story_summary": "豊田喜一郎が父の自動織機事業から自動車事業を分離独立。国産乗用車開発に挑戦し、戦時下で軍用車両を製造。",
    "before_state": "成長痛",
    "trigger_type": "意図的決断",
    "action_type": "攻める・挑戦",
    "after_state": "変質・新生",
    "before_hex": "震",
    "trigger_hex": "乾",
    "action_hex": "乾",
    "after_hex": "巽",
    "pattern_type": "Breakthrough",
    "outcome": "Mixed",
    "free_tags": [
      "#自動車",
      "#豊田喜一郎",
      "#国産車"
    ],
    "source_type": "book",
    "credibility_rank": "A",
    "main_domain": "自動車",
    "country": "JP"
  },
  {
    "target_name": "日本放送協会（NHK）設立",
    "scale": "other",
    "period": "1925-1945",
    "story_summary": "ラジオ放送の開始とともに設立。全国放送網を整備し、戦時下では国策放送を担った。敗戦後は民主化と再編を経験。",
    "before_state": "どん底・危機",
    "trigger_type": "意図的決断",
    "action_type": "攻める・挑戦",
    "after_state": "持続成長・大成功",
    "before_hex": "坎",
    "trigger_hex": "乾",
    "action_hex": "震",
    "after_hex": "離",
    "pattern_type": "Breakthrough",
    "outcome": "Success",
    "free_tags": [
      "#放送",
      "#NHK",
      "#メディア"
    ],
    "source_type": "book",
    "credibility_rank": "A",
    "main_domain": "メディア",
    "country": "JP"
  },
  {
    "target_name": "日本窒素肥料（チッソ）創業",
    "scale": "company",
    "period": "1908-1940",
    "story_summary": "野口遵が水力発電と化学工業を結合。硫安製造で成功し、電気化学工業のパイオニアとして急成長。",
    "before_state": "どん底・危機",
    "trigger_type": "意図的決断",
    "action_type": "攻める・挑戦",
    "after_state": "持続成長・大成功",
    "before_hex": "坎",
    "trigger_hex": "乾",
    "action_hex": "震",
    "after_hex": "乾",
    "pattern_type": "Breakthrough",
    "outcome": "Success",
    "free_tags": [
      "#化学",
      "#電気化学",
      "#肥料"
    ],
    "source_type": "book",
    "credibility_rank": "A",
    "main_domain": "化学",
    "country": "JP"
  }
]