[
  {
    "target_name": "パナソニックホールディングス（黒字リストラ）",
    "scale": "company",
    "period": "2025-2027",
    "story_summary": "3000億円超の純利益がある黒字企業でありながら、グローバルで1万人の人員削減を発表。白物家電事業を中心に不採算事業の終息や拠点統廃合を進め、700億円の収益改善を見込む。将来を見据えた先制的な組織再編。",
    "before_state": "安定・平和",
    "trigger_type": "意図的決断",
    "action_type": "刷新・破壊",
    "after_state": "変質・新生",
    "before_hex": "坤",
    "trigger_hex": "乾",
    "action_hex": "震",
    "after_hex": "艮",
    "pattern_type": "Pivot_Success",
    "outcome": "Mixed",
    "free_tags": ["#黒字リストラ", "#組織再編", "#電機業界", "#2025年"],
    "source_type": "news",
    "credibility_rank": "A",
    "source_url": "https://business.nikkei.com/atcl/gen/19/00801/101600001/",
    "logic_memo": "地水師（第7卦）初爻：軍の最初期、規律を整える段階。黒字の安定期に先手を打って組織を締め直す姿は、師の初爻「師出以律、否臧凶」（軍を出すには規律を以てす）に対応。規律なき改革は凶だが、パナソニックは計画的に進めている。",
    "yao_analysis": {
      "before_hexagram_id": 7,
      "before_yao_position": 1,
      "after_hexagram_id": 2,
      "after_yao_position": 1,
      "transition_type": "yao_change"
    }
  },
  {
    "target_name": "井上百貨店（松本）",
    "scale": "company",
    "period": "1885-2025",
    "story_summary": "1885年創業、140年の歴史を持つ長野県松本市の老舗百貨店。建物の老朽化とネットショッピング普及による来店者減少を受け、松本駅前の本店を閉店。郊外のショッピングセンターに事業を集約した戦略的撤退。",
    "before_state": "停滞・閉塞",
    "trigger_type": "外部ショック",
    "action_type": "捨てる・撤退",
    "after_state": "縮小安定・生存",
    "before_hex": "艮",
    "trigger_hex": "離",
    "action_hex": "巽",
    "after_hex": "坤",
    "pattern_type": "Slow_Decline",
    "outcome": "Mixed",
    "free_tags": ["#百貨店", "#老舗", "#撤退", "#長野県", "#2025年"],
    "source_type": "news",
    "credibility_rank": "A",
    "source_url": "https://www.nbs-tv.co.jp/news/articles/?cid=18304",
    "logic_memo": "天山遯（第33卦）初爻：退きの最初の段階、尾を垂れて危うし。140年の老舗が郊外に事業を集約して撤退する姿は、遯の初爻「遯尾、厲、勿用有攸往」（退く尾は危うい、進むべからず）に対応。無理に留まらず、慎重に退く判断。",
    "yao_analysis": {
      "before_hexagram_id": 33,
      "before_yao_position": 1,
      "after_hexagram_id": 13,
      "after_yao_position": 1,
      "transition_type": "yao_change"
    }
  },
  {
    "target_name": "株式会社BALM（旧ビッグモーター）",
    "scale": "company",
    "period": "2023-2024",
    "story_summary": "修理の過大見積りや不必要な修理、街路樹への除草剤散布などの不正行為が発覚し信用が失墜。負債831億円で民事再生法を申請。事業は伊藤忠系のWECARSに譲渡し、被害者対応と債務処理を担う。",
    "before_state": "絶頂・慢心",
    "trigger_type": "内部崩壊",
    "action_type": "捨てる・撤退",
    "after_state": "崩壊・消滅",
    "before_hex": "乾",
    "trigger_hex": "坎",
    "action_hex": "坤",
    "after_hex": "坎",
    "pattern_type": "Hubris_Collapse",
    "outcome": "Failure",
    "free_tags": ["#不正", "#民事再生", "#自動車販売", "#2024年"],
    "source_type": "news",
    "credibility_rank": "S",
    "source_url": "https://www.tsr-net.co.jp/news/tsr/detail/1200471_1521.html",
    "logic_memo": "水山蹇（第39卦）初爻：困難の始まり、行けば蹇み来たれば誉れあり。ビッグモーターの不正発覚は自ら招いた困難。初爻「往蹇来誉」（行けば難儀、来れば名誉）に対応。進み続けず、立ち止まって反省すべき時。",
    "yao_analysis": {
      "before_hexagram_id": 39,
      "before_yao_position": 1,
      "after_hexagram_id": 63,
      "after_yao_position": 1,
      "transition_type": "yao_change"
    }
  },
  {
    "target_name": "丸住製紙",
    "scale": "company",
    "period": "1919-2025",
    "story_summary": "1919年創業、業歴100年超の老舗製紙会社。デジタル化による紙需要の減少と原材料・エネルギー価格高騰により、2022年〜2023年に合計約267億円の最終赤字を計上。負債590億円で民事再生法を申請。",
    "before_state": "停滞・閉塞",
    "trigger_type": "外部ショック",
    "action_type": "耐える・潜伏",
    "after_state": "崩壊・消滅",
    "before_hex": "坤",
    "trigger_hex": "坎",
    "action_hex": "艮",
    "after_hex": "坎",
    "pattern_type": "Slow_Decline",
    "outcome": "Failure",
    "free_tags": ["#製紙業", "#老舗", "#民事再生", "#愛媛県", "#2025年"],
    "source_type": "news",
    "credibility_rank": "A",
    "source_url": "https://business.nikkei.com/atcl/seminar/21nv/00013/062600015/",
    "logic_memo": "水山蹇（第39卦）二爻：王臣蹇蹇、自らの身に非ず。100年企業がデジタル化という時代の波に抗えず困窮。二爻「王臣蹇蹇、匪躬之故」（王の臣として艱難に艱難を重ねる）に対応。自身の過失ではなく外部環境による困難。",
    "yao_analysis": {
      "before_hexagram_id": 39,
      "before_yao_position": 2,
      "after_hexagram_id": 48,
      "after_yao_position": 2,
      "transition_type": "yao_change"
    }
  },
  {
    "target_name": "ウエルシアHD・ツルハHD経営統合",
    "scale": "company",
    "period": "2024-2025",
    "story_summary": "2024年2月に資本業務提携を発表。2025年12月にウエルシアHDがツルハHDの完全子会社となり、売上高2兆3124億円、店舗数5659店の日本最大のドラッグストアチェーンが誕生。3年で500億円のシナジー効果を見込む。",
    "before_state": "安定・平和",
    "trigger_type": "意図的決断",
    "action_type": "対話・融合",
    "after_state": "変質・新生",
    "before_hex": "兌",
    "trigger_hex": "乾",
    "action_hex": "坤",
    "after_hex": "震",
    "pattern_type": "Pivot_Success",
    "outcome": "Success",
    "free_tags": ["#M&A", "#ドラッグストア", "#経営統合", "#2025年"],
    "source_type": "news",
    "credibility_rank": "A",
    "source_url": "https://www.mixonline.jp/tabid55.html?artid=78184",
    "logic_memo": "沢地萃（第45卦）四爻：大吉にして咎なし。業界最大手同士が統合し日本最大のドラッグストアチェーンを形成。四爻「大吉、无咎」に対応。萃（集合）の中位で、大きな結集が成功する段階。",
    "yao_analysis": {
      "before_hexagram_id": 45,
      "before_yao_position": 4,
      "after_hexagram_id": 8,
      "after_yao_position": 4,
      "transition_type": "yao_change"
    }
  },
  {
    "target_name": "KDDIによるローソンTOB",
    "scale": "company",
    "period": "2024",
    "story_summary": "KDDIが約5000億円を投じてローソン株50%を取得するTOBを実施。2024年7月にローソンは上場廃止し、三菱商事とKDDIの50%ずつの共同経営体制へ移行。小売×IT×物流を統合した新業態構築を目指す。",
    "before_state": "停滞・閉塞",
    "trigger_type": "意図的決断",
    "action_type": "対話・融合",
    "after_state": "変質・新生",
    "before_hex": "艮",
    "trigger_hex": "乾",
    "action_hex": "坤",
    "after_hex": "震",
    "pattern_type": "Pivot_Success",
    "outcome": "Mixed",
    "free_tags": ["#TOB", "#コンビニ", "#通信業界", "#異業種統合", "#2024年"],
    "source_type": "news",
    "credibility_rank": "A",
    "source_url": "https://www.nikkei.com/article/DGXZQOUC050YA0V00C24A2000000/",
    "logic_memo": "沢地萃（第45卦）五爻：萃に位あり、咎なし。リーダーの地位で集合を主導。KDDIが中核となり通信×小売の統合を牽引する姿は、五爻「萃有位、无咎」に対応。正当な立場での統合は咎なし。",
    "yao_analysis": {
      "before_hexagram_id": 45,
      "before_yao_position": 5,
      "after_hexagram_id": 17,
      "after_yao_position": 5,
      "transition_type": "yao_change"
    }
  },
  {
    "target_name": "伊藤忠商事によるデサント完全子会社化",
    "scale": "company",
    "period": "2024-2025",
    "story_summary": "伊藤忠商事がスポーツアパレル大手デサントに対して約1826億円のTOBを実施。2025年3月に完全子会社化が完了。スポーツ用品市場でのグループ連携強化を図る。",
    "before_state": "停滞・閉塞",
    "trigger_type": "意図的決断",
    "action_type": "対話・融合",
    "after_state": "縮小安定・生存",
    "before_hex": "艮",
    "trigger_hex": "乾",
    "action_hex": "坤",
    "after_hex": "坤",
    "pattern_type": "Steady_Growth",
    "outcome": "Success",
    "free_tags": ["#TOB", "#スポーツアパレル", "#完全子会社化", "#2025年"],
    "source_type": "news",
    "credibility_rank": "A",
    "source_url": "https://www.nihon-ma.co.jp/columns/2024/x20241223/",
    "logic_memo": "沢地萃（第45卦）上爻：齎諮涕洟、咎なし。集合の最終段階、涙を流しても咎なし。長年対立していた伊藤忠とデサントが和解し統合。上爻「齎諮涕洟、无咎」に対応。困難を経ての統合完了。",
    "yao_analysis": {
      "before_hexagram_id": 45,
      "before_yao_position": 6,
      "after_hexagram_id": 12,
      "after_yao_position": 6,
      "transition_type": "yao_change"
    }
  },
  {
    "target_name": "富士フイルムホールディングス（ヘルスケア転換）",
    "scale": "company",
    "period": "2003-2026",
    "story_summary": "写真フィルムの需要消滅という本業喪失の危機を乗り越え、ヘルスケアと半導体材料を成長の柱に事業転換。2024〜2026年度に約1.9兆円を投資し、2030年度に売上高4兆円を目指す。",
    "before_state": "どん底・危機",
    "trigger_type": "外部ショック",
    "action_type": "刷新・破壊",
    "after_state": "V字回復・大成功",
    "before_hex": "坎",
    "trigger_hex": "離",
    "action_hex": "震",
    "after_hex": "乾",
    "pattern_type": "Shock_Recovery",
    "outcome": "Success",
    "free_tags": ["#事業転換", "#ヘルスケア", "#半導体", "#V字回復"],
    "source_type": "news",
    "credibility_rank": "S",
    "source_url": "https://www.meti.go.jp/shingikai/sankoshin/shin_kijiku/value_creation/pdf/007_03_00.pdf",
    "logic_memo": "火風鼎（第50卦）上爻：鼎玉鉉、大吉。変革の完成、玉の取っ手を持つ鼎。フィルム事業からヘルスケアへの完全転換を成し遂げた富士フイルムは、鼎の上爻「鼎玉鉉、大吉、无不利」に対応。変革の最高到達点。",
    "yao_analysis": {
      "before_hexagram_id": 50,
      "before_yao_position": 6,
      "after_hexagram_id": 32,
      "after_yao_position": 6,
      "transition_type": "yao_change"
    }
  },
  {
    "target_name": "Intel（大規模リストラ）",
    "scale": "company",
    "period": "2024-2025",
    "story_summary": "Intelは9.95万人から7.5万人へ2.4万人の人員削減を実施し、主要工場プロジェクトを停止。AI開発へのリソース再配分を目的とした、同社史上最大の構造改革。",
    "before_state": "停滞・閉塞",
    "trigger_type": "外部ショック",
    "action_type": "刷新・破壊",
    "after_state": "変質・新生",
    "before_hex": "艮",
    "trigger_hex": "震",
    "action_hex": "震",
    "after_hex": "坎",
    "pattern_type": "Pivot_Success",
    "outcome": "Mixed",
    "free_tags": ["#半導体", "#リストラ", "#AI", "#USA", "#2024年"],
    "source_type": "news",
    "credibility_rank": "A",
    "source_url": "https://intellizence.com/insights/layoff-downsizing/major-companies-that-announced-mass-layoffs/",
    "logic_memo": "沢雷随（第17卦）初爻：官に渝りあり、貞にして吉。変化に随う最初の段階。Intelが時代の変化（AI）に対応して組織を大きく変える姿は、随の初爻「官有渝、貞吉」に対応。正しく変化に随えば吉。",
    "yao_analysis": {
      "before_hexagram_id": 17,
      "before_yao_position": 1,
      "after_hexagram_id": 45,
      "after_yao_position": 1,
      "transition_type": "yao_change"
    }
  },
  {
    "target_name": "Spirit Airlines（破産申請）",
    "scale": "company",
    "period": "2018-2024",
    "story_summary": "米国最大の格安航空会社が破産保護を申請。株価は2018年以降97%下落し、2020年以降の累積損失は25億ドル超。2025-2026年に10億ドル以上の債務返済を控え、経営再建を目指す。",
    "before_state": "停滞・閉塞",
    "trigger_type": "外部ショック",
    "action_type": "耐える・潜伏",
    "after_state": "崩壊・消滅",
    "before_hex": "艮",
    "trigger_hex": "坎",
    "action_hex": "艮",
    "after_hex": "坎",
    "pattern_type": "Slow_Decline",
    "outcome": "Failure",
    "free_tags": ["#航空業界", "#破産", "#格安航空", "#USA", "#2024年"],
    "source_type": "news",
    "credibility_rank": "A",
    "source_url": "https://www.cnn.com/2024/12/22/business/2024-company-bankruptcy-list",
    "logic_memo": "沢水困（第47卦）五爻：鼻を劓られ足を刖られる、赤紱に困しむ。困窮の極み、上位者も苦しむ。格安航空の雄が破産に追い込まれた姿は、困の五爻に対応。高い地位にあっても困難から逃れられない。",
    "yao_analysis": {
      "before_hexagram_id": 47,
      "before_yao_position": 5,
      "after_hexagram_id": 40,
      "after_yao_position": 5,
      "transition_type": "yao_change"
    }
  },
  {
    "target_name": "Tupperware（破産申請）",
    "scale": "company",
    "period": "1946-2024",
    "story_summary": "キッチン用品の象徴的ブランドが長年の人気低下と財務問題の末に破産申請。負債12億ドル超に対し資産は6.8億ドル。直販ビジネスモデルの衰退とプラスチックからガラスへの消費者シフトが背景。",
    "before_state": "停滞・閉塞",
    "trigger_type": "外部ショック",
    "action_type": "耐える・潜伏",
    "after_state": "崩壊・消滅",
    "before_hex": "坤",
    "trigger_hex": "離",
    "action_hex": "艮",
    "after_hex": "坎",
    "pattern_type": "Slow_Decline",
    "outcome": "Failure",
    "free_tags": ["#消費財", "#破産", "#直販", "#USA", "#2024年"],
    "source_type": "news",
    "credibility_rank": "A",
    "source_url": "https://www.cnn.com/2024/12/22/business/2024-company-bankruptcy-list",
    "logic_memo": "雷火豊（第55卦）上爻：其の屋を豊にし、其の家を蔀う。豊かさの極みで暗くなる。かつて家庭の象徴だったTupperwareが破産に至る姿は、豊の上爻「豊其屋、蔀其家、闚其戸、闃其无人」に対応。繁栄の終焉。",
    "yao_analysis": {
      "before_hexagram_id": 55,
      "before_yao_position": 6,
      "after_hexagram_id": 30,
      "after_yao_position": 6,
      "transition_type": "yao_change"
    }
  },
  {
    "target_name": "Netflix（Warner Bros.買収）",
    "scale": "company",
    "period": "2025",
    "story_summary": "NetflixがWarner Bros.（HBO Max、HBO、映画・TVスタジオ含む）を企業価値827億ドルで買収。Netflixの「自前主義」からの初の大型M&Aで、ストリーミング業界の再編を象徴。",
    "before_state": "絶頂・慢心",
    "trigger_type": "意図的決断",
    "action_type": "攻める・挑戦",
    "after_state": "変質・新生",
    "before_hex": "乾",
    "trigger_hex": "乾",
    "action_hex": "乾",
    "after_hex": "震",
    "pattern_type": "Pivot_Success",
    "outcome": "Mixed",
    "free_tags": ["#M&A", "#ストリーミング", "#メディア", "#USA", "#2025年"],
    "source_type": "news",
    "credibility_rank": "A",
    "source_url": "https://www.cnbc.com/2025/12/05/neflix-warner-bros-discovery-deal.html",
    "logic_memo": "震為雷（第51卦）上爻：震索索、視矍矍。雷の極み、恐れおののく。業界を震撼させる大型買収は、震の上爻に対応。最上位での衝撃的行動だが、「征凶」の警告も。統合リスクに注意が必要。",
    "yao_analysis": {
      "before_hexagram_id": 51,
      "before_yao_position": 6,
      "after_hexagram_id": 21,
      "after_yao_position": 6,
      "transition_type": "yao_change"
    }
  },
  {
    "target_name": "Walmart（AI転換）",
    "scale": "company",
    "period": "2024-2025",
    "story_summary": "伝統的小売大手からテクノロジーファースト企業への転換。AIエージェントをバリューチェーン全体に展開し、45億ドルの生産性向上を達成。オンライン売上は全体の18%に成長、4四半期連続で20%成長。",
    "before_state": "安定・平和",
    "trigger_type": "意図的決断",
    "action_type": "刷新・破壊",
    "after_state": "V字回復・大成功",
    "before_hex": "坤",
    "trigger_hex": "乾",
    "action_hex": "震",
    "after_hex": "乾",
    "pattern_type": "Steady_Growth",
    "outcome": "Success",
    "free_tags": ["#小売", "#AI", "#DX", "#USA", "#2025年"],
    "source_type": "news",
    "credibility_rank": "A",
    "source_url": "https://corporate.walmart.com/news/2024/10/09/walmart-reveals-plan-for-scaling-artificial-intelligence-generative-ai-augmented-reality-and-immersive-commerce-experiences",
    "logic_memo": "風山漸（第53卦）上爻：鴻漸于陸、其の羽用て儀と為すべし。漸進の完成、高みに達する。小売からテック企業への漸進的転換を成功させたWalmartは、漸の上爻「鴻漸于陸」に対応。着実な進歩の到達点。",
    "yao_analysis": {
      "before_hexagram_id": 53,
      "before_yao_position": 6,
      "after_hexagram_id": 39,
      "after_yao_position": 6,
      "transition_type": "yao_change"
    }
  },
  {
    "target_name": "日産自動車（Re:Nissan計画）",
    "scale": "company",
    "period": "2024-2027",
    "story_summary": "2025年3月期に6709億円の最終赤字を計上し、「Re:Nissan」再建計画を発表。グループ従業員の15%にあたる2万人を削減し、世界7工場を閉鎖。生産能力を250万台に引き下げ。",
    "before_state": "どん底・危機",
    "trigger_type": "内部崩壊",
    "action_type": "刷新・破壊",
    "after_state": "変質・新生",
    "before_hex": "坎",
    "trigger_hex": "坎",
    "action_hex": "震",
    "after_hex": "艮",
    "pattern_type": "Shock_Recovery",
    "outcome": "Mixed",
    "free_tags": ["#自動車", "#リストラ", "#再建", "#2024年"],
    "source_type": "news",
    "credibility_rank": "A",
    "source_url": "https://toyokeizai.net/articles/-/877960",
    "logic_memo": "地火明夷（第36卦）初爻：明夷于飛、垂其翼。明るさが傷つく初期、翼を垂れて飛ぶ。大赤字から再建を開始する日産は、明夷の初爻に対応。「君子于行、三日不食」―困難な旅路の始まり。",
    "yao_analysis": {
      "before_hexagram_id": 36,
      "before_yao_position": 1,
      "after_hexagram_id": 15,
      "after_yao_position": 1,
      "transition_type": "yao_change"
    }
  },
  {
    "target_name": "イトーヨーカドー（北海道撤退）",
    "scale": "company",
    "period": "1975-2025",
    "story_summary": "1975年から約50年間展開していた北海道から完全撤退。2024年6月から段階的に6店舗を閉店し、2025年1月のアリオ札幌店閉店で撤退完了。オンライン消費シフトや地域密着型スーパーとの競争激化が背景。",
    "before_state": "停滞・閉塞",
    "trigger_type": "外部ショック",
    "action_type": "捨てる・撤退",
    "after_state": "縮小安定・生存",
    "before_hex": "艮",
    "trigger_hex": "離",
    "action_hex": "巽",
    "after_hex": "坤",
    "pattern_type": "Slow_Decline",
    "outcome": "Mixed",
    "free_tags": ["#小売", "#撤退", "#北海道", "#2025年"],
    "source_type": "news",
    "credibility_rank": "A",
    "source_url": "https://coki.jp/article/news/44114/",
    "logic_memo": "火山旅（第56卦）三爻：旅焚其次、喪其童僕。旅の途中で宿が焼ける。50年展開した北海道からの撤退は、旅の三爻「旅焚其次」に対応。拠点を失う苦しみ、しかし旅は続く。",
    "yao_analysis": {
      "before_hexagram_id": 56,
      "before_yao_position": 3,
      "after_hexagram_id": 35,
      "after_yao_position": 3,
      "transition_type": "yao_change"
    }
  },
  {
    "target_name": "Raiffeisen Bank（ロシア撤退）",
    "scale": "company",
    "period": "2022-2025",
    "story_summary": "オーストリア最大の西側銀行がロシア事業の縮小と売却を検討。撤退決定に対しロシアの裁判所から21億ドル超の賠償命令を受ける。地政学リスクによる市場撤退の困難を示す事例。",
    "before_state": "安定・平和",
    "trigger_type": "外部ショック",
    "action_type": "捨てる・撤退",
    "after_state": "迷走・混乱",
    "before_hex": "坤",
    "trigger_hex": "坎",
    "action_hex": "巽",
    "after_hex": "坎",
    "pattern_type": "Shock_Recovery",
    "outcome": "Mixed",
    "free_tags": ["#銀行", "#地政学リスク", "#ロシア", "#撤退", "#2025年"],
    "source_type": "news",
    "credibility_rank": "A",
    "source_url": "https://tdcenter.org/2025/04/17/a-market-in-decline-why-business-as-usual-no-longer-works-with-russia/",
    "logic_memo": "火山旅（第56卦）五爻：雉を射て一矢亡う、終に以て誉命あり。旅の高位、犠牲を払って名誉を得る。多大な損失を被りながらも撤退を決断したRaiffeisenは、旅の五爻に対応。",
    "yao_analysis": {
      "before_hexagram_id": 56,
      "before_yao_position": 5,
      "after_hexagram_id": 33,
      "after_yao_position": 5,
      "transition_type": "yao_change"
    }
  },
  {
    "target_name": "Red Lobster（破産からの再生）",
    "scale": "company",
    "period": "2024",
    "story_summary": "世界最大のシーフードレストランチェーンが負債10億ドル超、現金3000万ドル未満で破産申請。マーケティング・品質・サービスへの投資不足が競争力低下を招いた。2024年9月に新オーナーの下で破産から脱却。",
    "before_state": "停滞・閉塞",
    "trigger_type": "内部崩壊",
    "action_type": "耐える・潜伏",
    "after_state": "変質・新生",
    "before_hex": "艮",
    "trigger_hex": "坎",
    "action_hex": "艮",
    "after_hex": "震",
    "pattern_type": "Shock_Recovery",
    "outcome": "Mixed",
    "free_tags": ["#外食", "#破産", "#再生", "#USA", "#2024年"],
    "source_type": "news",
    "credibility_rank": "A",
    "source_url": "https://www.cnn.com/2024/12/22/business/2024-company-bankruptcy-list",
    "logic_memo": "水風井（第48卦）上爻：井收勿幕、有孚元吉。井戸の完成、覆いをかけるな。破産から再生し新たな所有者の下で再出発したRed Lobsterは、井の上爻に対応。水源は枯れておらず、正しく活用すれば大吉。",
    "yao_analysis": {
      "before_hexagram_id": 48,
      "before_yao_position": 6,
      "after_hexagram_id": 57,
      "after_yao_position": 6,
      "transition_type": "yao_change"
    }
  },
  {
    "target_name": "Google（Wiz買収）",
    "scale": "company",
    "period": "2025",
    "story_summary": "Googleがクラウドセキュリティ企業Wizを320億ドルで買収。史上最大級のサイバーセキュリティM&Aで、テクノロジー業界のクラウドセキュリティ統合の潮流を反映。",
    "before_state": "絶頂・慢心",
    "trigger_type": "意図的決断",
    "action_type": "対話・融合",
    "after_state": "V字回復・大成功",
    "before_hex": "乾",
    "trigger_hex": "乾",
    "action_hex": "坤",
    "after_hex": "乾",
    "pattern_type": "Steady_Growth",
    "outcome": "Success",
    "free_tags": ["#M&A", "#サイバーセキュリティ", "#クラウド", "#USA", "#2025年"],
    "source_type": "news",
    "credibility_rank": "A",
    "source_url": "https://imaa-institute.org/blog/2025-top-global-m-and-a-deals/",
    "logic_memo": "風水渙（第59卦）初爻：馬壮を用て拯う、吉。散らばりを救う初期段階。クラウドセキュリティの分散を統合するWiz買収は、渙の初爻「用拯馬壮、吉」に対応。力強い手段で散逸を防ぐ。",
    "yao_analysis": {
      "before_hexagram_id": 59,
      "before_yao_position": 1,
      "after_hexagram_id": 61,
      "after_yao_position": 1,
      "transition_type": "yao_change"
    }
  },
  {
    "target_name": "ConocoPhillips（Marathon Oil買収）",
    "scale": "company",
    "period": "2024",
    "story_summary": "ConocoPhillipsがMarathon Oilを企業価値225億ドルで買収完了。Bakken、Eagle Ford、Permian各地域の資産を統合し、マルチベースン統合企業としての地位を強化。",
    "before_state": "安定・平和",
    "trigger_type": "意図的決断",
    "action_type": "対話・融合",
    "after_state": "V字回復・大成功",
    "before_hex": "坤",
    "trigger_hex": "乾",
    "action_hex": "坤",
    "after_hex": "乾",
    "pattern_type": "Steady_Growth",
    "outcome": "Success",
    "free_tags": ["#M&A", "#エネルギー", "#石油", "#USA", "#2024年"],
    "source_type": "news",
    "credibility_rank": "A",
    "source_url": "https://www.conocophillips.com/news-media/story/conocophillips-completes-acquisition-of-marathon-oil/",
    "logic_memo": "風水渙（第59卦）四爻：渙其群、元吉。群れを散らして大吉。複数の石油資産を統合し再編成するConocoPhillipsは、渙の四爻に対応。既存の枠組みを解いて新たな統合を図る。",
    "yao_analysis": {
      "before_hexagram_id": 59,
      "before_yao_position": 4,
      "after_hexagram_id": 6,
      "after_yao_position": 4,
      "transition_type": "yao_change"
    }
  }
]
