[
  {
    "target_name": "富士フイルム デジタル化危機からの多角化成功（2000-2015）",
    "scale": "company",
    "period": "2000-2015",
    "story_summary": "写真フィルム市場のデジタル化で本業が消滅の危機。技術資産を活かした多角化（化粧品、医療機器、半導体材料）でV字回復を果たした。",
    "before_state": "どん底・危機",
    "trigger_type": "外部ショック",
    "action_type": "刷新・破壊",
    "after_state": "持続成長・大成功",
    "before_hex": "坤",
    "trigger_hex": "坎",
    "action_hex": "震",
    "after_hex": "乾",
    "pattern_type": "Shock_Recovery",
    "outcome": "Success",
    "free_tags": ["#富士フイルム", "#デジタル化", "#多角化", "#技術転用"],
    "source_type": "news",
    "credibility_rank": "S",
    "main_domain": "製造業",
    "sources": ["https://ilink-corp.co.jp/2658.html"],
    "changing_lines_1": [1, 4],
    "changing_lines_2": [2, 5],
    "changing_lines_3": [3, 6],
    "logic_memo": "坤（本業消滅危機）→坎（デジタル化ショック）→震（抜本変革）→乾（多角化成功）"
  },
  {
    "target_name": "ベルフェイス コロナ禍ピボットで復活（2020-2023）",
    "scale": "company",
    "period": "2020-2023",
    "story_summary": "コロナ禍でWeb会議ツール普及により解約続出、100人規模のリストラで倒産危機。金融機関向け特化にピボットし復活。",
    "before_state": "どん底・危機",
    "trigger_type": "外部ショック",
    "action_type": "捨てる・撤退",
    "after_state": "安定・平和",
    "before_hex": "坤",
    "trigger_hex": "坎",
    "action_hex": "巽",
    "after_hex": "艮",
    "pattern_type": "Crisis_Pivot",
    "outcome": "Success",
    "free_tags": ["#ベルフェイス", "#ピボット", "#SaaS", "#金融特化"],
    "source_type": "news",
    "credibility_rank": "A",
    "main_domain": "IT・テック",
    "sources": ["https://sogyotecho.jp/pivot-matome/"],
    "changing_lines_1": [2, 5],
    "changing_lines_2": [3, 6],
    "changing_lines_3": [1, 4],
    "logic_memo": "坤（倒産危機）→坎（競合台頭）→巽（ピボット撤退）→艮（安定回復）"
  },
  {
    "target_name": "パナソニック 2期連続7000億円赤字からV字回復（2012-2014）",
    "scale": "company",
    "period": "2012-2014",
    "story_summary": "2012年に2期連続7000億円超の赤字。選択と集中で不採算事業から撤退し、2014年には純利益1000億円超に回復。",
    "before_state": "どん底・危機",
    "trigger_type": "内部崩壊",
    "action_type": "捨てる・撤退",
    "after_state": "V字回復・大成功",
    "before_hex": "坤",
    "trigger_hex": "坎",
    "action_hex": "巽",
    "after_hex": "乾",
    "pattern_type": "Shock_Recovery",
    "outcome": "Success",
    "free_tags": ["#パナソニック", "#選択と集中", "#構造改革"],
    "source_type": "news",
    "credibility_rank": "S",
    "main_domain": "製造業",
    "sources": ["https://www.sungrove.co.jp/v-shaped-recovery/"],
    "changing_lines_1": [1, 4],
    "changing_lines_2": [2, 5],
    "changing_lines_3": [3, 6],
    "logic_memo": "坤（巨額赤字）→坎（構造問題）→巽（選択と集中）→乾（黒字回復）"
  },
  {
    "target_name": "日産自動車 ゴーン改革によるV字回復（1999-2002）",
    "scale": "company",
    "period": "1999-2002",
    "story_summary": "1999年に6844億円の赤字で当時上場企業ワースト。ゴーン氏のコスト削減とリバイバルプランで2002年に完全復活。",
    "before_state": "どん底・危機",
    "trigger_type": "意図的決断",
    "action_type": "刷新・破壊",
    "after_state": "V字回復・大成功",
    "before_hex": "坤",
    "trigger_hex": "震",
    "action_hex": "震",
    "after_hex": "乾",
    "pattern_type": "Shock_Recovery",
    "outcome": "Success",
    "free_tags": ["#日産", "#カルロスゴーン", "#リバイバルプラン"],
    "source_type": "news",
    "credibility_rank": "S",
    "main_domain": "製造業",
    "sources": ["https://pro-d-use.jp/blog/v-shaped-recovery/"],
    "changing_lines_1": [2, 5],
    "changing_lines_2": [3, 6],
    "changing_lines_3": [1, 4],
    "logic_memo": "坤（巨額赤字）→震（ゴーン就任）→震（激しい改革）→乾（完全復活）"
  },
  {
    "target_name": "ペヤング 異物混入事件からの復活（2014-2015）",
    "scale": "company",
    "period": "2014-2015",
    "story_summary": "2014年異物混入事件で全商品販売停止・自主回収。半年間の工場停止後、再発防止策を徹底して復活、シェア1位に返り咲き。",
    "before_state": "成長痛",
    "trigger_type": "内部崩壊",
    "action_type": "耐える・潜伏",
    "after_state": "V字回復・大成功",
    "before_hex": "震",
    "trigger_hex": "坎",
    "action_hex": "艮",
    "after_hex": "乾",
    "pattern_type": "Crisis_Pivot",
    "outcome": "Success",
    "free_tags": ["#ペヤング", "#まるか食品", "#異物混入", "#品質管理"],
    "source_type": "news",
    "credibility_rank": "S",
    "main_domain": "食品・飲料",
    "sources": ["https://mag.sendenkaigi.com/senden/201803/brand-revived/012693.php"],
    "changing_lines_1": [1, 4],
    "changing_lines_2": [2, 5],
    "changing_lines_3": [3, 6],
    "logic_memo": "震（成長中）→坎（異物混入危機）→艮（停止・改善）→乾（シェア1位復活）"
  },
  {
    "target_name": "ゑびや（EBILAB）DX変革で売上8.5倍（2014-2023）",
    "scale": "company",
    "period": "2014-2023",
    "story_summary": "創業100年超の老舗食堂が売上低迷で事業縮小検討。AI需要予測システム導入で売上8.5倍、営業利益10倍を達成。",
    "before_state": "停滞・閉塞",
    "trigger_type": "意図的決断",
    "action_type": "刷新・破壊",
    "after_state": "持続成長・大成功",
    "before_hex": "艮",
    "trigger_hex": "震",
    "action_hex": "震",
    "after_hex": "乾",
    "pattern_type": "Steady_Growth",
    "outcome": "Success",
    "free_tags": ["#ゑびや", "#EBILAB", "#DX", "#老舗変革", "#AI活用"],
    "source_type": "news",
    "credibility_rank": "A",
    "main_domain": "小売・サービス",
    "sources": ["https://pulse-ai.jp/media/【社長必読】中小企業の組織変革成功事例集/"],
    "changing_lines_1": [2, 5],
    "changing_lines_2": [3, 6],
    "changing_lines_3": [1, 4],
    "logic_memo": "艮（停滞老舗）→震（新社長決断）→震（DX導入）→乾（売上8.5倍）"
  },
  {
    "target_name": "湖池屋 組織風土改革で復活（2016-2020）",
    "scale": "company",
    "period": "2016-2020",
    "story_summary": "指示待ち体質と保守的風土で停滞。新社長就任で「思考力と主体性」をテーマに組織改革、プライドポテトなど新商品で復活。",
    "before_state": "停滞・閉塞",
    "trigger_type": "意図的決断",
    "action_type": "刷新・破壊",
    "after_state": "持続成長・大成功",
    "before_hex": "艮",
    "trigger_hex": "震",
    "action_hex": "震",
    "after_hex": "乾",
    "pattern_type": "Steady_Growth",
    "outcome": "Success",
    "free_tags": ["#湖池屋", "#組織改革", "#プライドポテト"],
    "source_type": "news",
    "credibility_rank": "A",
    "main_domain": "食品・飲料",
    "sources": ["https://media.unipos.me/organizational-climate-reform-case-study"],
    "changing_lines_1": [1, 4],
    "changing_lines_2": [2, 5],
    "changing_lines_3": [3, 6],
    "logic_memo": "艮（停滞・指示待ち）→震（新社長改革）→震（組織変革）→乾（ブランド復活）"
  },
  {
    "target_name": "神栄 製糸業からセンサー世界トップへ（1970-2000）",
    "scale": "company",
    "period": "1970-2000",
    "story_summary": "1887年創業の製糸業。1983年に製糸業撤退後、1970年代開発の金属酸化物型センサに集中し湿度センサで世界トップシェア獲得。",
    "before_state": "停滞・閉塞",
    "trigger_type": "外部ショック",
    "action_type": "捨てる・撤退",
    "after_state": "持続成長・大成功",
    "before_hex": "艮",
    "trigger_hex": "坎",
    "action_hex": "巽",
    "after_hex": "乾",
    "pattern_type": "Crisis_Pivot",
    "outcome": "Success",
    "free_tags": ["#神栄", "#業態転換", "#センサー", "#老舗"],
    "source_type": "news",
    "credibility_rank": "A",
    "main_domain": "製造業",
    "sources": ["https://www.axa.co.jp/100-year-life/business/20180920/"],
    "changing_lines_1": [2, 5],
    "changing_lines_2": [3, 6],
    "changing_lines_3": [1, 4],
    "logic_memo": "艮（製糸業停滞）→坎（業界衰退）→巽（製糸撤退）→乾（センサートップ）"
  }
]
