[
  {
    "target_name": "梶山智大氏・リニア新幹線技術者から北海道起業（2020-2022）",
    "scale": "individual",
    "period": "2020-2022",
    "story_summary": "東京でJR東海リニア中央新幹線の国家プロジェクトに携わる技術者だった梶山智大氏が、奥様の千裕さんとともに北海道へ地方移住を決断。妻のキャリアを活かせる中札内村を選択、移住2年で起業成功。プロジェクトでの評価を捨て、新天地での挑戦を選んだ転身。",
    "before_state": "安定・平和",
    "trigger_type": "意図的決断",
    "action_type": "捨てる・撤退",
    "after_state": "安定・平和",
    "before_hex": "離",
    "trigger_hex": "巽",
    "action_hex": "震",
    "after_hex": "坤",
    "pattern_type": "Pivot_Success",
    "outcome": "Success",
    "free_tags": ["#地方移住", "#起業", "#キャリアチェンジ"],
    "source_type": "news",
    "credibility_rank": "B",
    "changing_lines_1": [2, 5],
    "changing_lines_2": [3, 6],
    "changing_lines_3": [1, 4],
    "country": "日本",
    "life_domain": "キャリア",
    "sources": ["https://nobels.co.jp/nobelswave/country_living/fuufu/"],
    "confidence_percent": 85,
    "evidence_notes": "JR東海リニア新幹線プロジェクト技術者。北海道中札内村へ移住。2年で起業成功。妻のキャリア重視で地域選択",
    "logic_memo": "離（国家プロジェクト）→巽（移住検討）→震（東京撤退）→坤（地方定着）。安定を捨てて新天地へ"
  },
  {
    "target_name": "Tさん・東京SE青森UターンWeb起業（2018-2020）",
    "scale": "individual",
    "period": "2018-2020",
    "story_summary": "東京の大学で情報工学を学びシステムエンジニアとして就職したTさんが、東京で人脈形成・受注基盤構築後、28歳で結婚を機に青森県十和田市にUターン。地元でWeb制作会社設立、東京時代のネットワークを活かして地方起業成功。",
    "before_state": "安定・平和",
    "trigger_type": "偶発・出会い",
    "action_type": "対話・融合",
    "after_state": "安定・平和",
    "before_hex": "離",
    "trigger_hex": "兌",
    "action_hex": "巽",
    "after_hex": "坤",
    "pattern_type": "Pivot_Success",
    "outcome": "Success",
    "free_tags": ["#Uターン", "#Web起業", "#地方創生"],
    "source_type": "news",
    "credibility_rank": "B",
    "changing_lines_1": [3, 5],
    "changing_lines_2": [2, 4],
    "changing_lines_3": [1, 6],
    "country": "日本",
    "life_domain": "キャリア",
    "sources": ["https://www.rals.net/journal/country-life/rural-established-success/"],
    "confidence_percent": 80,
    "evidence_notes": "東京大学で情報工学、SE就職。28歳結婚機にUターン。青森県十和田市でWeb制作会社設立。東京人脈活用",
    "logic_memo": "離（東京SE）→兌（結婚出会い）→巽（段階的準備）→坤（地元定着）。人脈を保ちながら地方転身"
  },
  {
    "target_name": "宮本翼氏・江別市ピッツェリア起業（2022）",
    "scale": "individual",
    "period": "2020-2022",
    "story_summary": "宮本翼氏が北海道江別市の特産品・小麦を使ったピッツェリア「PIZZERIA DEL CAPITANO」を2022年4月に起業。地元食材を活かし食を通じて地域魅力をアピール。地方でのニッチ市場開拓に成功。",
    "before_state": "停滞・閉塞",
    "trigger_type": "意図的決断",
    "action_type": "攻める・挑戦",
    "after_state": "安定・平和",
    "before_hex": "離",
    "trigger_hex": "乾",
    "action_hex": "巽",
    "after_hex": "離",
    "pattern_type": "Steady_Growth",
    "outcome": "Success",
    "free_tags": ["#地方起業", "#飲食店", "#地域資源"],
    "source_type": "news",
    "credibility_rank": "B",
    "changing_lines_1": [2, 5],
    "changing_lines_2": [3, 6],
    "changing_lines_3": [1, 4],
    "country": "日本",
    "life_domain": "キャリア",
    "sources": ["https://www.rals.net/journal/country-life/rural-established-success/"],
    "confidence_percent": 80,
    "evidence_notes": "2022年4月北海道江別市でピッツェリア開業。地元小麦使用。食を通じた地域アピール",
    "logic_memo": "離（飲食業志向）→乾（起業決断）→巽（地域特化）→離（地域ブランド）。地域資源を活用"
  },
  {
    "target_name": "佐藤豊彦氏・地域おこし協力隊から福祉起業（2018-2021）",
    "scale": "individual",
    "period": "2018-2021",
    "story_summary": "佐藤豊彦氏が栃木県那珂川町で地域おこし協力隊として活動、任期終了後に合同会社「繋ごう農村」を設立。高齢者向け生活支援サービス・移動販売・コミュニティナースの取り組みを展開。地域課題を事業化して成功。",
    "before_state": "安定・平和",
    "trigger_type": "意図的決断",
    "action_type": "対話・融合",
    "after_state": "安定・平和",
    "before_hex": "離",
    "trigger_hex": "坤",
    "action_hex": "巽",
    "after_hex": "離",
    "pattern_type": "Steady_Growth",
    "outcome": "Success",
    "free_tags": ["#地域おこし", "#福祉", "#社会課題解決"],
    "source_type": "news",
    "credibility_rank": "B",
    "changing_lines_1": [3, 5],
    "changing_lines_2": [2, 4],
    "changing_lines_3": [1, 6],
    "country": "日本",
    "life_domain": "キャリア",
    "sources": ["https://www.rals.net/journal/country-life/rural-established-success/"],
    "confidence_percent": 80,
    "evidence_notes": "栃木県那珂川町地域おこし協力隊。任期後合同会社繋ごう農村設立。高齢者支援・移動販売・コミュニティナース展開",
    "logic_memo": "離（協力隊評価）→坤（地域基盤）→巽（段階的事業化）→離（地域貢献）。地域との信頼関係を事業に"
  },
  {
    "target_name": "40代SE男性・大手電機から異業界転職（2023-2024）",
    "scale": "individual",
    "period": "2023-2024",
    "story_summary": "大手電機メーカーで商品企画・マーケティングに携わった40代半ば男性が、40代半ばにして初転職を決意。経験を活かせる類似業界ではなく敢えて異業界への挑戦を目指し、転職活動は難航するも最終的に2社の内定獲得。新分野で再スタート成功。",
    "before_state": "安定・平和",
    "trigger_type": "意図的決断",
    "action_type": "攻める・挑戦",
    "after_state": "安定・平和",
    "before_hex": "離",
    "trigger_hex": "艮",
    "action_hex": "乾",
    "after_hex": "離",
    "pattern_type": "Pivot_Success",
    "outcome": "Success",
    "free_tags": ["#40代転職", "#異業界", "#キャリアチェンジ"],
    "source_type": "news",
    "credibility_rank": "B",
    "changing_lines_1": [2, 5],
    "changing_lines_2": [3, 6],
    "changing_lines_3": [1, 4],
    "country": "日本",
    "life_domain": "キャリア",
    "sources": ["https://www.bizreach.jp/testimonial/view/29/"],
    "confidence_percent": 85,
    "evidence_notes": "大手電機メーカー商品企画・マーケティング。40代半ば初転職。異業界挑戦で2社内定。2024年転職成功",
    "logic_memo": "離（大手企業評価）→艮（キャリア限界）→乾（異業界挑戦）→離（新分野確立）。安定を捨てて新挑戦"
  }
]
