[
  {
    "target_name": "東ドイツ_社会主義の実験と崩壊",
    "scale": "country",
    "period": "1949-1990",
    "story_summary": "ソ連占領地域に成立した社会主義国家。シュタージ（秘密警察）による監視社会、ベルリンの壁で「逃亡防止」。スポーツ強国として威信誇示も経済は西に大敗。1989年ハンガリー経由の脱出が雪崩を打ち、壁崩壊で国家消滅。",
    "before_state": "停滞・閉塞",
    "trigger_type": "外部ショック",
    "action_type": "逃げる・放置",
    "after_state": "崩壊・消滅",
    "before_hex": "艮",
    "trigger_hex": "坎",
    "action_hex": "巽",
    "after_hex": "坤",
    "pattern_type": "Hubris_Collapse",
    "outcome": "Failure",
    "free_tags": ["#東ドイツ", "#ベルリンの壁", "#シュタージ", "#社会主義", "#崩壊"],
    "source_type": "book",
    "credibility_rank": "S",
    "logic_memo": "監視社会の停滞（艮）→ハンガリー開放の衝撃（坎）→対応できず放置（巽）→国家消滅（坤）"
  },
  {
    "target_name": "ユーゴスラビア_多民族国家の分裂",
    "scale": "country",
    "period": "1945-1992",
    "story_summary": "チトーが多民族をまとめた「ユーゴスラビア連邦」。非同盟運動のリーダーとして国際的地位確立。しかしチトー死後、民族主義が台頭。1991年以降スロベニア、クロアチア、ボスニアが独立、内戦で20万人以上死亡。民族浄化の悲劇。",
    "before_state": "安定・平和",
    "trigger_type": "内部崩壊",
    "action_type": "刷新・破壊",
    "after_state": "崩壊・消滅",
    "before_hex": "坤",
    "trigger_hex": "艮",
    "action_hex": "離",
    "after_hex": "坤",
    "pattern_type": "Hubris_Collapse",
    "outcome": "Failure",
    "free_tags": ["#ユーゴスラビア", "#チトー", "#民族浄化", "#内戦", "#分裂"],
    "source_type": "book",
    "credibility_rank": "S",
    "logic_memo": "チトー時代の安定（坤）→民族主義で内部崩壊（艮）→独立で分裂（離）→国家消滅（坤）"
  },
  {
    "target_name": "チェコスロバキア_ビロード革命と離婚",
    "scale": "country",
    "period": "1968-1993",
    "story_summary": "1968年「プラハの春」はソ連軍に弾圧され20年の停滞。1989年ビロード革命で民主化、ハヴェル大統領誕生。しかし1993年にチェコとスロバキアが平和的に分離。「ビロード離婚」として無血分離の模範例に。",
    "before_state": "停滞・閉塞",
    "trigger_type": "外部ショック",
    "action_type": "刷新・破壊",
    "after_state": "変質・新生",
    "before_hex": "艮",
    "trigger_hex": "坎",
    "action_hex": "離",
    "after_hex": "兌",
    "pattern_type": "Pivot_Success",
    "outcome": "Success",
    "free_tags": ["#チェコスロバキア", "#プラハの春", "#ビロード革命", "#ハヴェル", "#分離"],
    "source_type": "book",
    "credibility_rank": "S",
    "logic_memo": "弾圧後の停滞（艮）→東欧革命の衝撃（坎）→体制刷新（離）→二国として新生（兌）"
  },
  {
    "target_name": "ハンガリー_動乱から EU懐疑派へ",
    "scale": "country",
    "period": "1956-2024",
    "story_summary": "1956年のハンガリー動乱はソ連に弾圧。しかし「グヤーシュ共産主義」で相対的自由を確保。1989年最初に鉄のカーテンを開いた国に。EU加盟後はオルバン政権の権威主義化、EUとの対立が続く。「非自由主義民主主義」を自称。",
    "before_state": "どん底・危機",
    "trigger_type": "意図的決断",
    "action_type": "耐える・潜伏",
    "after_state": "変質・新生",
    "before_hex": "坎",
    "trigger_hex": "離",
    "action_hex": "坤",
    "after_hex": "兌",
    "pattern_type": "Endurance",
    "outcome": "Mixed",
    "free_tags": ["#ハンガリー", "#動乱", "#オルバン", "#EU懐疑派", "#権威主義"],
    "source_type": "news",
    "credibility_rank": "S",
    "logic_memo": "動乱後のどん底（坎）→改革の決断（離）→体制内で耐える（坤）→独自路線へ変質（兌）"
  },
  {
    "target_name": "ルーマニア_チャウシェスク処刑と移行",
    "scale": "country",
    "period": "1965-2024",
    "story_summary": "チャウシェスクの個人崇拝、秘密警察セクリターテによる恐怖政治。1989年革命でチャウシェスク夫妻は即決裁判で処刑。しかし旧共産党幹部が権力維持、2007年EU加盟も汚職問題が続く。「未完の革命」との評価。",
    "before_state": "停滞・閉塞",
    "trigger_type": "外部ショック",
    "action_type": "刷新・破壊",
    "after_state": "安定成長・成功",
    "before_hex": "艮",
    "trigger_hex": "坎",
    "action_hex": "離",
    "after_hex": "坤",
    "pattern_type": "Shock_Recovery",
    "outcome": "Mixed",
    "free_tags": ["#ルーマニア", "#チャウシェスク", "#革命", "#処刑", "#EU"],
    "source_type": "book",
    "credibility_rank": "S",
    "logic_memo": "独裁の停滞（艮）→革命の衝撃（坎）→体制刷新（離）→EU加盟で安定（坤）"
  }
]
