[
  {
    "target_name": "子育て世帯支援拡充（2024年）",
    "scale": "family",
    "period": "2024",
    "story_summary": "児童手当が2024年10月から拡充。所得制限撤廃、高校生まで延長、第3子以降3万円に増額。異次元の少子化対策の一環。子育て世帯の経済的負担軽減を図る。財源確保が今後の課題。",
    "before_state": "成長痛",
    "trigger_type": "意図的決断",
    "action_type": "対話・融合",
    "after_state": "安定・平和",
    "before_hex": "兌",
    "trigger_hex": "離",
    "action_hex": "兌",
    "after_hex": "坤",
    "pattern_type": "Endurance",
    "outcome": "Success",
    "free_tags": ["#児童手当", "#拡充", "#所得制限撤廃", "#第3子", "#少子化対策", "#2024年10月"],
    "source_type": "news",
    "credibility_rank": "A",
    "logic_memo": "子育て負担（兌）→拡充決断（離）→制度設計対話（兌）→負担軽減（坤）"
  },
  {
    "target_name": "こども誰でも通園制度（2024年）",
    "scale": "family",
    "period": "2024",
    "story_summary": "保護者の就労要件なしで保育施設を利用できる「こども誰でも通園制度」が2024年度から試行。月10時間まで利用可能。在宅育児家庭の孤立防止と負担軽減が狙い。2026年度本格実施予定。",
    "before_state": "停滞・閉塞",
    "trigger_type": "意図的決断",
    "action_type": "刷新・破壊",
    "after_state": "変質・新生",
    "before_hex": "巽",
    "trigger_hex": "離",
    "action_hex": "離",
    "after_hex": "巽",
    "pattern_type": "Pivot_Success",
    "outcome": "Success",
    "free_tags": ["#通園", "#保育", "#就労要件", "#孤立防止", "#在宅育児", "#こども"],
    "source_type": "news",
    "credibility_rank": "A",
    "logic_memo": "在宅育児孤立（巽）→新制度決断（離）→制度刷新（離）→支援拡大（巽）"
  },
  {
    "target_name": "出産一時金増額（2023年）",
    "scale": "family",
    "period": "2023-2024",
    "story_summary": "出産育児一時金が2023年4月から42万円から50万円に増額。出産費用の上昇に対応。2024年も産科医療体制の維持が課題。出産費用の見える化も推進。安心して出産できる環境整備が継続。",
    "before_state": "成長痛",
    "trigger_type": "意図的決断",
    "action_type": "守る・維持",
    "after_state": "安定・平和",
    "before_hex": "兌",
    "trigger_hex": "離",
    "action_hex": "坤",
    "after_hex": "坤",
    "pattern_type": "Endurance",
    "outcome": "Success",
    "free_tags": ["#出産一時金", "#50万円", "#出産費用", "#産科医療", "#見える化", "#増額"],
    "source_type": "news",
    "credibility_rank": "A",
    "logic_memo": "出産費用負担（兌）→増額決断（離）→制度維持（坤）→負担軽減（坤）"
  },
  {
    "target_name": "共同親権導入（2024年）",
    "scale": "family",
    "period": "2024",
    "story_summary": "離婚後の共同親権を認める民法改正が2024年成立。2026年施行予定。単独親権の見直しで子の利益を重視。DV・虐待ケースへの配慮も規定。面会交流の円滑化と養育費確保が期待される。",
    "before_state": "停滞・閉塞",
    "trigger_type": "意図的決断",
    "action_type": "刷新・破壊",
    "after_state": "変質・新生",
    "before_hex": "兌",
    "trigger_hex": "離",
    "action_hex": "離",
    "after_hex": "巽",
    "pattern_type": "Pivot_Success",
    "outcome": "Success",
    "free_tags": ["#共同親権", "#民法改正", "#離婚", "#子の利益", "#面会交流", "#2026年"],
    "source_type": "news",
    "credibility_rank": "A",
    "logic_memo": "単独親権で課題（兌）→法改正決断（離）→制度刷新（離）→新制度（巽）"
  },
  {
    "target_name": "不妊治療保険適用拡大効果（2022-2024）",
    "scale": "family",
    "period": "2022-2024",
    "story_summary": "2022年4月からの不妊治療保険適用で治療件数が増加。経済的負担軽減で治療開始のハードル低下。2024年も利用拡大継続。体外受精の成功率向上も報告。少子化対策の一環として評価。",
    "before_state": "停滞・閉塞",
    "trigger_type": "意図的決断",
    "action_type": "対話・融合",
    "after_state": "変質・新生",
    "before_hex": "巽",
    "trigger_hex": "離",
    "action_hex": "兌",
    "after_hex": "巽",
    "pattern_type": "Pivot_Success",
    "outcome": "Success",
    "free_tags": ["#不妊治療", "#保険適用", "#体外受精", "#少子化対策", "#2022年", "#経済負担"],
    "source_type": "news",
    "credibility_rank": "A",
    "logic_memo": "治療費負担で停滞（巽）→保険適用決断（離）→医療機関と対話（兌）→利用拡大（巽）"
  }
]
